import java.util.Enumeration;

public class ez extends cg {
  public short aM = -1;
  
  public short aN = -1;
  
  public short aO = -1;
  
  public short aP = -1;
  
  public short aQ = -1;
  
  public short aR = -1;
  
  public short aS = -1;
  
  public short aT = -1;
  
  public short aU = -1;
  
  public short aV = -1;
  
  public long aW;
  
  public dq aX = null;
  
  public int aY;
  
  public int aZ;
  
  public int ba;
  
  public int bb;
  
  public int bc;
  
  public int bd;
  
  public int be;
  
  public int bf;
  
  public int bg;
  
  public int bh;
  
  public int bi;
  
  public int bj;
  
  public int bk;
  
  private int a;
  
  public int bl;
  
  public int bm;
  
  public int bn;
  
  public int bo;
  
  public int bp;
  
  public int bq;
  
  private int b;
  
  private int c = 0;
  
  public int br;
  
  public int bs;
  
  public int bt;
  
  public int bu;
  
  public int bv;
  
  public int bw;
  
  private int d;
  
  public byte bx;
  
  public short by;
  
  public short bz;
  
  public short bA = -1;
  
  public long bB;
  
  public long bC;
  
  public int bD = 0;
  
  int bE = 0;
  
  public boolean bF = false;
  
  public boolean bG;
  
  public boolean bH = false;
  
  public boolean bI = false;
  
  public boolean bJ = false;
  
  public boolean bK = false;
  
  public long bL = 0L;
  
  public long bM = 0L;
  
  public long bN = 0L;
  
  public long bO = 0L;
  
  public long bP = 0L;
  
  public long bQ = 0L;
  
  public int bR;
  
  public int bS;
  
  public int bT;
  
  public int bU;
  
  private int e;
  
  public long bV;
  
  public int bW = 2;
  
  public int bX = 1;
  
  public int bY = 2;
  
  public int bZ = 2;
  
  public int ca = 2;
  
  public int cb = 2;
  
  public int cc = -1;
  
  public int cd = -1;
  
  public int ce;
  
  private byte[] f = new byte[] { 
      0, 0, 0, 0, 0, 0, 0, 1, 1, 1, 
      1, 1 };
  
  public byte[] cf = new byte[] { 2, 2, 2, 3, 3, 3 };
  
  private static byte g;
  
  public static byte cg = 0;
  
  public static int ch = 0;
  
  public static int ci = 0;
  
  public int cj;
  
  public int ck;
  
  public int cl;
  
  public int cm;
  
  private int h = 0;
  
  public int cn = 0;
  
  public byte co = 0;
  
  public boolean cp = false;
  
  public static String[] cq = null;
  
  public static byte cr = 0;
  
  public byte cs;
  
  public int ct;
  
  public byte cu;
  
  public byte cv = -1;
  
  public byte cw;
  
  public byte cx = 0;
  
  public byte cy;
  
  public int cz = -1;
  
  public short cA = 0;
  
  public String cB = "";
  
  public String cC = df.ai;
  
  public String cD = "";
  
  public String cE = null;
  
  public int cF;
  
  public int cG;
  
  public int cH;
  
  public int cI = 0;
  
  public int cJ = 0;
  
  public boolean cK;
  
  private boolean i = false;
  
  public boolean cL;
  
  public boolean cM;
  
  public short[] cN;
  
  public em cO = null;
  
  public int cP;
  
  public int cQ;
  
  public es cR;
  
  public int cS;
  
  public int cT;
  
  public boolean cU = false;
  
  public boolean cV = false;
  
  public boolean cW = false;
  
  public boolean cX = false;
  
  public long cY;
  
  public static aq cZ;
  
  public static aq da;
  
  public static aq db;
  
  public static aq dc;
  
  public static aq dd;
  
  public static aq de = null;
  
  public es df = new es("MainObject vecBuff");
  
  public ds dg;
  
  public dh dh;
  
  public int di;
  
  public boolean dj = false;
  
  public cj dk;
  
  private boolean j;
  
  public int dl = 0;
  
  public int dm = -1;
  
  public do dn;
  
  public static es do = new es("MainObject vecCapchar");
  
  public static String dp = "";
  
  public boolean dq = false;
  
  public boolean dr;
  
  public boolean ds;
  
  public static byte dt;
  
  public es du = new es("MainObject VecEffauto");
  
  public es dv = new es("Low VecEffauto");
  
  public es dw = new es("Effect CharWearing");
  
  private es k = new es();
  
  public int dx;
  
  public boolean dy;
  
  public int dz = 0;
  
  public int dA = 1500;
  
  public byte dB;
  
  public boolean dC;
  
  public boolean dD;
  
  public boolean dE = false;
  
  public short[] dF = new short[] { -1, -1, -1, -1, -1, -1, -1 };
  
  public static short[] dG;
  
  public short dH;
  
  public boolean dI = false;
  
  public boolean dJ = false;
  
  public boolean dK = false;
  
  public boolean dL = false;
  
  public boolean dM = false;
  
  public byte dN = -1;
  
  public byte dO = -1;
  
  public boolean dP;
  
  public boolean dQ = false;
  
  public boolean dR;
  
  public byte dS = 1;
  
  public byte dT = 0;
  
  private static byte[] l = new byte[] { 0, 1, 2, 1 };
  
  private byte m = 0;
  
  private static byte[][] n = new byte[][] { { 6, 1, 2, 5, 4, 3, 6 }, { 6, 1, 2, 5, 4, 3, 6 }, { 6, 1, 2, 5, 4, 3, 6 }, { 6, 1, 2, 5, 4, 3, 6 } };
  
  private int[][][] o = new int[][][] { { new int[9], new int[9], new int[9] }, { { 0, 0, 0, 1, 1, 1, 2, 2, 2 }, { 1, 1, 1, 2, 2, 2 }, { 2, 2, 2, 1, 1, 1 } }, { { 2, 2, 2, 2, 2, 3, 3, 3, 3 }, { 2, 2, 2, 2, 2, 3, 3, 3, 3 }, { 2, 2, 2, 2, 2, 3, 3, 3, 3 } }, { { 4, 4, 4, 4, 4, 4, 4, 4, 4 }, { 4, 4, 4, 4, 4, 4, 4, 4, 4 }, { 4, 4, 4, 4, 4, 4, 4, 4, 4 } }, { { 4, 4, 4, 4, 4, 4, 4, 4, 4 }, { 4, 4, 4, 4, 4, 4, 4, 4, 4 }, { 4, 4, 4, 4, 4, 4, 4, 4, 4 } } };
  
  private int p;
  
  private int q;
  
  private byte r;
  
  private byte s;
  
  private byte t;
  
  private static ek u = new ek();
  
  private int v;
  
  private byte w;
  
  private byte x;
  
  private byte y;
  
  private int z;
  
  private int A = 0;
  
  private static byte[] B = new byte[] { 2, 2, 2, 3, 3, 4, 4, 4 };
  
  private byte C = 0;
  
  private byte D = 0;
  
  public boolean dU = true;
  
  private byte E;
  
  public int dV = 0;
  
  public int dW = 0;
  
  public int dX = -1;
  
  public static am[][][] dY = new am[4][][];
  
  private int F = 0;
  
  private int[] G = new int[] { 0, 0, 0, 1, 1, 1, 2, 2, 2 };
  
  public boolean dZ = false;
  
  public int ea = 0;
  
  public int eb = 0;
  
  public int ec = 0;
  
  public int ed = 0;
  
  public byte ee = -1;
  
  public byte ef;
  
  public byte eg;
  
  private static byte[] H = new byte[] { 3 };
  
  private static byte[] I = new byte[] { 2, 2, 2, 3, 3, 3 };
  
  private short[][] J = new short[12][];
  
  public byte[] eh = new byte[] { -1, -1, -1 };
  
  private ce K;
  
  public static ce[] ei;
  
  private int L = 0;
  
  private int M = 0;
  
  private int N = 0;
  
  private byte O = 0;
  
  private byte P = 8;
  
  private byte[] Q = new byte[] { 2, 2, 2 };
  
  private byte[][] R = new byte[][] { { -2, 4, 2, -10 }, { -2, 4, 2, -10 } };
  
  private byte[][] S = new byte[][] { { 6, 5, 5, 2 }, { 6, 5, 5, 2 } };
  
  public static boolean f(int paramInt) {
    try {
      for (byte b = 0; b < dG.length; b++) {
        if (dG[b] == paramInt)
          return true; 
      } 
      return false;
    } catch (Exception exception) {
      dw.a("----Err mainobj:-- isMaHopNguyenLieu");
      return false;
    } 
  }
  
  public String f() {
    return "";
  }
  
  public ez() {}
  
  public boolean c_() {
    return false;
  }
  
  public boolean D() {
    return false;
  }
  
  public void d(int paramInt) {}
  
  public boolean B() {
    return false;
  }
  
  public boolean C() {
    return false;
  }
  
  public ez(int paramInt1, byte paramByte, String paramString, int paramInt2, int paramInt3) {
    this.ct = paramInt1;
    this.cB = paramString;
    this.cu = paramByte;
    this.aY = paramInt2;
    this.aZ = paramInt3;
    this.bf = paramInt2;
    this.bg = paramInt3;
    this.cG = 0;
  }
  
  public void a(byte paramByte1, short paramShort1, short paramShort2, byte paramByte2, byte paramByte3, byte paramByte4, String paramString1, String paramString2, short paramShort3, short paramShort4, byte paramByte5, byte paramByte6, byte[] paramArrayOfbyte1, byte[] paramArrayOfbyte2, byte[] paramArrayOfbyte3) {}
  
  public final void a(int paramInt1, int paramInt2, int paramInt3) {
    if (paramInt2 < 8)
      paramInt2 += 8; 
    this.bX = paramInt1;
    this.ca = paramInt2;
    this.cb = paramInt3;
    this.bU = paramInt2;
  }
  
  public void a(int paramInt1, int paramInt2, short paramShort) {}
  
  public final void a(int paramInt1, int paramInt2, int paramInt3, int paramInt4, int paramInt5, int paramInt6, int paramInt7, byte[] paramArrayOfbyte, byte paramByte1, long paramLong, byte paramByte2, int paramInt8, int paramInt9) {
    dq dq1 = new dq(paramInt1, paramInt2, paramInt3, 0, 0, 0, 0, paramArrayOfbyte, paramLong, paramByte2, paramInt8, paramInt9);
    if (paramByte1 == 0) {
      for (paramInt3 = 0; paramInt3 < this.du.c(); paramInt3++) {
        dq dq2;
        if ((dq2 = (dq)this.du.a(paramInt3)) != null && dq2.d == paramInt1)
          this.du.d(dq2); 
      } 
      this.du.a(dq1);
      return;
    } 
    for (paramInt3 = 0; paramInt3 < this.dv.c(); paramInt3++) {
      dq dq2;
      if ((dq2 = (dq)this.dv.a(paramInt3)) != null && dq2.d == paramInt1)
        this.dv.d(dq2); 
    } 
    this.dv.a(dq1);
  }
  
  public final void a(int paramInt1, int paramInt2, int paramInt3, int paramInt4, int paramInt5, int paramInt6, int paramInt7) {
    if (D())
      this.du.d(); 
    for (paramInt4 = 0; paramInt4 < this.du.c(); paramInt4++) {
      dq dq2;
      if ((dq2 = (dq)this.du.a(paramInt4)) != null && dq2.d == paramInt1)
        this.du.d(dq2); 
    } 
    dq dq1 = new dq(paramInt1, paramInt2, paramInt3, 0, 0, paramInt6, 0);
    this.du.a(dq1);
  }
  
  public final boolean E() {
    return !(this.cv != 12 && this.cv != 13 && this.cv != 11);
  }
  
  public static void c(bx parambx, int paramInt1, int paramInt2) {
    parambx.a(dc, 0, 0, aq.a(dc.a), aq.b(dc.a), 0, paramInt1, paramInt2, 3);
  }
  
  public boolean x() {
    return false;
  }
  
  public final void a(byte[] paramArrayOfbyte) {
    try {
      if (paramArrayOfbyte == null) {
        this.bY = -1;
        this.bZ = -1;
        this.bW = -1;
        this.cc = -1;
        this.cb = -1;
        this.ca = -1;
        this.bX = -1;
        this.dX = -1;
        this.cd = -1;
        return;
      } 
      this.bY = paramArrayOfbyte[0];
      this.bZ = paramArrayOfbyte[1];
      this.bW = paramArrayOfbyte[2];
      this.cc = paramArrayOfbyte[7];
      byte b;
      if ((b = this.bx) == 3) {
        b = 2;
      } else if (b == 2) {
        b = 3;
      } 
      this.dX = paramArrayOfbyte[b + 8];
      return;
    } catch (Exception exception2) {
      Exception exception1;
      (exception1 = null).printStackTrace();
      return;
    } 
  }
  
  public final void b(byte[] paramArrayOfbyte) {
    if (paramArrayOfbyte == null) {
      this.bY = -1;
      this.bZ = -1;
      this.bW = -1;
      this.cc = -1;
      this.dX = -1;
      this.cd = -1;
      return;
    } 
    this.bY = paramArrayOfbyte[1];
    this.bZ = paramArrayOfbyte[7];
    this.bW = paramArrayOfbyte[6];
    this.cc = paramArrayOfbyte[10];
    this.dX = paramArrayOfbyte[0];
    this.cd = paramArrayOfbyte[5];
  }
  
  public void a(bx parambx) {}
  
  public final void e(bx parambx) {
    if (this.df == null)
      return; 
    for (int i = this.df.c() - 1; i >= 0; i--) {
      ei ei;
      if ((ei = (ei)this.df.a(i)) != null && ei.b)
        if (ei.h == 4) {
          ei.a(parambx, this.aY + this.bn, this.aZ - this.be + 5 + this.bo);
        } else {
          ei.a(parambx, this.aY + this.bn, this.aZ + this.bo);
        }  
    } 
  }
  
  public final void f(bx parambx) {
    if (this.df == null)
      return; 
    for (int i = this.df.c() - 1; i >= 0; i--) {
      ei ei;
      if ((ei = (ei)this.df.a(i)) != null && !ei.b)
        if (ei.h == 4) {
          ei.a(parambx, this.aY + this.bn, this.aZ - this.be + 5 + this.bo);
        } else {
          ei.a(parambx, this.aY + this.bn, this.aZ + this.bo);
        }  
    } 
  }
  
  public void a(bx parambx, int paramInt1, int paramInt2) {
    if (this.bX != -1)
      ak.d(2, this.bX).a(parambx, paramInt1 - 1, paramInt2 + 23, 0, 0); 
    if (this.ca != -1)
      ak.d(4, this.ca).a(parambx, paramInt1 - 1, paramInt2 + 23, 0, 0); 
    if (this.cb != -1)
      ak.d(5, this.cb).a(parambx, paramInt1 - 1, paramInt2 + 23, 0, 0); 
    if (this.bW != -1)
      ak.d(3, this.bW).a(parambx, paramInt1 - 1, paramInt2 + 23, 0, 0); 
  }
  
  public final String c(String paramString) {
    String str = this.cB;
    if (this.cO != null)
      str = String.valueOf(this.cO.c) + paramString + str; 
    return str;
  }
  
  public final void a(bx parambx, int paramInt1, int paramInt2, int paramInt3) {
    if (this.cO != null) {
      fd fd = bk.i(this.cO.a);
      if (paramInt3 == 2) {
        paramInt3 = (o.j.a(this.cO.c) + 12) / 2;
        if (fd.a != null) {
          if (aq.b(fd.a.a) / 18 == 3) {
            if (ft.ai % 6 == 0) {
              int i;
              if ((i = l.length) == 0)
                i = 1; 
              this.m = (byte)((this.m + 1) % i);
            } 
            parambx.a(fd.a, 0, l[this.m] * 18, 18, 18, 0, paramInt1 - paramInt3 + 6, paramInt2, 3);
          } else {
            parambx.a(fd.a, paramInt1 - paramInt3 + 6, paramInt2, 3);
          } 
          bw.r.a(paramInt1 - paramInt3 + 6, paramInt2 - 1, this.cO.a(), 14, parambx, 0);
        } 
        o.j.a(parambx, this.cO.c, paramInt1 - paramInt3 + 15, paramInt2 - 6, 0, true);
        return;
      } 
      if (paramInt3 == 0) {
        if (fd.a != null) {
          if (aq.b(fd.a.a) / 18 == 3) {
            if (ft.ai % 6 == 0) {
              if ((paramInt3 = l.length) == 0)
                paramInt3 = 1; 
              this.m = (byte)((this.m + 1) % paramInt3);
            } 
            parambx.a(fd.a, 0, l[this.m] * 18, 18, 18, 0, paramInt1, paramInt2, 3);
          } else {
            parambx.a(fd.a, paramInt1, paramInt2, 3);
          } 
          bw.r.a(paramInt1 - 1, paramInt2 - 1, this.cO.a(), 14, parambx, 0);
        } 
        o.f.a(parambx, this.cO.c, paramInt1 + 13, paramInt2, 0, true);
        return;
      } 
      if (paramInt3 == -1) {
        if (fd.a != null) {
          if (aq.b(fd.a.a) / 18 == 3) {
            if (ft.ai % 6 == 0) {
              if ((paramInt3 = l.length) == 0)
                paramInt3 = 1; 
              this.m = (byte)((this.m + 1) % paramInt3);
            } 
            parambx.a(fd.a, 0, l[this.m] * 18, 18, 18, 0, paramInt1 - 1, paramInt2, 3);
          } else {
            parambx.a(fd.a, paramInt1 - 1, paramInt2, 3);
          } 
          bw.r.a(paramInt1 - 1, paramInt2 - 1, this.cO.a(), 14, parambx, 0);
          return;
        } 
      } else if (paramInt3 == -2) {
        paramInt3 = (o.j.a(String.valueOf(this.cO.c) + " - " + this.cO.d) + 15) / 2;
        if (fd.a != null) {
          if (aq.b(fd.a.a) / 18 == 3) {
            if (ft.ai % 6 == 0) {
              int i;
              if ((i = l.length) == 0)
                i = 1; 
              this.m = (byte)((this.m + 1) % i);
            } 
            parambx.a(fd.a, 0, l[this.m] * 18, 18, 18, 0, paramInt1 - paramInt3 + 7, paramInt2, 3);
          } else {
            parambx.a(fd.a, paramInt1 - paramInt3 + 7, paramInt2, 3);
          } 
          bw.r.a(paramInt1 - paramInt3 + 6, paramInt2 - 1, this.cO.a(), 14, parambx, 0);
        } 
        o.j.a(parambx, String.valueOf(this.cO.c) + " - " + this.cO.d, paramInt1 - paramInt3 + 15, paramInt2 - 6, 0, true);
      } 
    } 
  }
  
  public final void g(bx parambx) {
    fd fd;
    if ((fd = bk.a((short)this.cS)).a != null) {
      this.be = aq.b(fd.a.a) / this.dB;
      this.bd = aq.a(fd.a.a);
      parambx.a(fd.a, 0, ft.ai / 7 % this.dB * this.be, this.bd, this.be, 0, this.aY, this.aZ, 33);
    } 
    if (cn.h == null || (cn.h != null && this != cn.h) || cf.I)
      a(parambx, 0); 
    int i = this.aY;
    int j = this.aZ - this.be - 8;
    int k = 0;
    if (this.bs > 0) {
      if (this.br > 0)
        if ((k = this.br * 50 / this.bs) <= 0) {
          k = 1;
        } else if (k > 50) {
          k = 50;
        }  
      parambx.a(-8714722);
      parambx.c(i - this.bd / 2 + 10, j, 50, 5);
      parambx.a(-579511);
      parambx.c(i - this.bd / 2 + 10, j, k, 5);
    } 
  }
  
  public final void F() {
    this.j = true;
    this.bw = 0;
    this.d = 10;
    this.p = 5;
    this.q = 72;
  }
  
  public final void b(bx parambx, int paramInt) {
    if (!this.bF) {
      if (ab()) {
        if (this.cF == 4 && !this.bI) {
          parambx.a(db, this.aY + 1, this.aZ + 1, 3);
          f(parambx);
          cg.aC.b(0, this.aY + 1, this.aZ - this.bo + 5, 0, 33, parambx);
          if (this.aX != null) {
            this.bI = false;
            this.bQ = dw.a();
            cn.a(15, this.aY, this.aZ);
            this.aX = null;
          } 
          if (this.h == 0)
            parambx.a(cg.ao, this.aY + 1, this.aZ - this.bo + 5 - 24, 17); 
        } else if (!aa()) {
          if (this.bA == -1 && this.aP == -1)
            parambx.a(db, this.aY + 1, this.aZ - this.bo + 2, 3); 
          f(parambx);
          g(parambx, this.aY, this.aZ);
          e(parambx, this.aY, this.aZ);
          paramInt = ((this.cG == 0 || this.cG == 2 || this.cG == 3) && ((this.bx == 3 && this.ce != 4) || (this.bx != 3 && this.ce != 5))) ? 1 : 0;
          boolean bool = false;
          if (this.bA != -1) {
            fd fd;
            if ((fd = bk.c(this.bA)).a != null) {
              int i;
              if ((i = this.cF) > this.o.length - 1)
                i = 0; 
              this.be = aq.b(fd.a.a) / 3;
              this.bd = aq.a(fd.a.a) / 2;
              if (this.ca == 4 || this.ca == 2)
                i = 3; 
              int j = 0;
              paramInt = 0;
              j = this.o[i][(this.cG > 2) ? 2 : this.cG][this.ce] / 3 * this.bd;
              paramInt = this.o[i][(this.cG > 2) ? 2 : this.cG][this.ce] % 3 * this.be;
              parambx.a(fd.a, j, paramInt, this.bd, this.be, (this.cG > 2) ? 2 : 0, this.aY, this.aZ - this.bj + this.bk, 33);
            } 
          } else {
            if (paramInt != 0)
              try {
                d(parambx, 0);
              } catch (Exception exception) {} 
            bool = false;
            for (byte b = 0; b < (n[this.cG]).length; b++) {
              byte b1;
              if (((b1 = n[this.cG][b]) != 6 && b1 != 4) || (b1 == 6 && this.cG == 1 && b == 7) || (b1 == 6 && this.cG != 1 && b == 0) || (b1 == 4 && this.cG != 1))
                if (q(b) >= 0) {
                  if (this.ee == -1) {
                    ak.d(b1, q(b)).a(parambx, this.aY, this.aZ - this.bo - this.bj + this.bk - this.bw, this.cG, this.ce);
                  } else if (b != 1) {
                    ak.d(b1, q(b)).a(parambx, this.aY, this.aZ - this.bo - this.bj + this.bk - this.eb - this.bw, this.cG, this.ce);
                  } else {
                    m(parambx);
                  } 
                } else if ((b1 == 0 || b1 == 1 || b1 == 2 || b1 == 4 || b1 == 5) && !bool) {
                  bool = true;
                  ac();
                }  
            } 
            if (this.ee != -1)
              l(parambx); 
            if (paramInt == 0)
              try {
                d(parambx, 0);
              } catch (Exception exception) {} 
          } 
        } else {
          for (paramInt = 0; paramInt < (n[this.cG]).length; paramInt++) {
            byte b;
            if ((b = n[this.cG][paramInt]) == 4 && q(paramInt) >= 0)
              if (this.ee == -1) {
                ak.d(b, q(paramInt)).a(parambx, this.aY, this.aZ - this.bo - this.bj + this.bk - this.bw, this.cG, this.ce);
              } else if (paramInt != 1) {
                ak.d(b, q(paramInt)).a(parambx, this.aY, this.aZ - this.bo - this.bj + this.bk - this.eb - this.bw, this.cG, this.ce);
              } else {
                m(parambx);
              }  
          } 
        } 
        if (!aa()) {
          f(parambx, this.aY, this.aZ);
          if (!this.dQ && this.cV && this.bj == 0) {
            paramInt = 1;
            if (this.cG == 2) {
              paramInt += 2;
            } else if (this.cG == 3) {
              paramInt -= 2;
            } 
            parambx.a(dd, 0, ((this.cF != 0) ? 2 : 0) * 17 + ft.ai / 2 % 2 * 17, 28, 17, 0, this.aY + paramInt, this.aZ - this.bo - 2 + this.bk, 3);
          } 
        } 
      } 
      if (!aa()) {
        if (cf.I || this != cn.h)
          a(parambx, 0); 
        e(parambx);
        k(parambx);
        d(parambx, this.aY, this.aZ);
        if (this.br > 0)
          h(parambx); 
      } 
    } 
  }
  
  private int q() {
    return (this.cG == 0) ? (this.ce + this.s * 18) : ((this.cG == 1) ? (this.cG * 6 + this.ce + this.s * 18) : (this.ce + 12 + this.s * 18));
  }
  
  private int r() {
    return (this.cG == 0) ? (this.ce + this.r * 18) : ((this.cG == 1) ? (this.cG * 6 + this.ce + this.r * 18) : (this.ce + 12 + this.r * 18));
  }
  
  private int s() {
    return (this.cG == 0) ? (this.ce + this.v * 18) : ((this.cG == 1) ? (this.cG * 6 + this.ce + this.v * 18) : (this.ce + 12 + this.v * 18));
  }
  
  private int u() {
    return (this.cG == 0) ? (this.ce + this.x * 18) : ((this.cG == 1) ? (this.cG * 6 + this.ce + this.x * 18) : (this.ce + 12 + this.x * 18));
  }
  
  private int W() {
    return (this.cG == 0) ? (this.ce + this.w * 18) : ((this.cG == 1) ? (this.cG * 6 + this.ce + this.w * 18) : (this.ce + 12 + this.w * 18));
  }
  
  private int a(int paramInt) {
    return paramInt + this.x * 18;
  }
  
  private int b(int paramInt) {
    return paramInt + this.w * 18;
  }
  
  private int k(int paramInt) {
    return paramInt + this.r * 18;
  }
  
  private int l(int paramInt) {
    return paramInt + this.s * 18;
  }
  
  private int X() {
    return (this.cG == 0) ? (this.A + this.z * 21) : ((this.cG == 1) ? (this.A + 7 + this.z * 21) : (this.A + 14 + this.z * 21));
  }
  
  private int m(int paramInt) {
    return paramInt + this.v * 18;
  }
  
  private int n(int paramInt) {
    return paramInt + this.C * 18;
  }
  
  private int o(int paramInt) {
    return paramInt + this.D * 18;
  }
  
  private int Y() {
    return (this.cG == 0) ? (this.ce + this.C * 18) : ((this.cG == 1) ? (this.cG * 6 + this.ce + this.C * 18) : (this.ce + 12 + this.C * 18));
  }
  
  private int Z() {
    return (this.cG == 0) ? (this.ce + this.D * 18) : ((this.cG == 1) ? (this.cG * 6 + this.ce + this.D * 18) : (this.ce + 12 + this.D * 18));
  }
  
  public static at g(int paramInt) {
    if (paramInt == -1)
      return null; 
    at at;
    if ((at = (at)u.a((new StringBuffer(String.valueOf(paramInt))).toString())) == null) {
      (at = new at(paramInt)).g = 113;
      u.a((new StringBuffer(String.valueOf(paramInt))).toString(), at);
      fp.a((short)paramInt, at.g);
      at.e = (int)(dw.a() / 1000L);
    } else {
      at.e = ft.aj;
    } 
    return at;
  }
  
  public static void G() {
    ek ek1;
    Enumeration enumeration = (ek1 = u).a.keys();
    while (enumeration.hasMoreElements()) {
      String str = enumeration.nextElement();
      at at = (at)u.a(str);
      if ((ft.aj - at.e) / 1000L > 60L)
        u.a(str); 
    } 
  }
  
  public final void c(bx parambx, int paramInt) {
    // Byte code:
    //   0: aload_0
    //   1: getfield cF : I
    //   4: iconst_2
    //   5: if_icmpne -> 26
    //   8: aload_0
    //   9: getfield aP : S
    //   12: iconst_m1
    //   13: if_icmpeq -> 26
    //   16: aload_0
    //   17: aload_0
    //   18: getfield ce : I
    //   21: iconst_1
    //   22: iadd
    //   23: putfield A : I
    //   26: aload_0
    //   27: getfield bF : Z
    //   30: ifne -> 4123
    //   33: aload_0
    //   34: invokespecial ab : ()Z
    //   37: ifeq -> 3831
    //   40: aload_0
    //   41: getfield cF : I
    //   44: iconst_4
    //   45: if_icmpne -> 184
    //   48: aload_0
    //   49: getfield bI : Z
    //   52: ifne -> 184
    //   55: aload_1
    //   56: getstatic ez.db : Laq;
    //   59: aload_0
    //   60: getfield aY : I
    //   63: iconst_1
    //   64: iadd
    //   65: aload_0
    //   66: getfield aZ : I
    //   69: iconst_1
    //   70: iadd
    //   71: iconst_3
    //   72: invokevirtual a : (Laq;III)V
    //   75: aload_0
    //   76: aload_1
    //   77: invokevirtual f : (Lbx;)V
    //   80: getstatic cg.aC : Lce;
    //   83: iconst_0
    //   84: aload_0
    //   85: getfield aY : I
    //   88: iconst_1
    //   89: iadd
    //   90: aload_0
    //   91: getfield aZ : I
    //   94: aload_0
    //   95: getfield bo : I
    //   98: isub
    //   99: iconst_5
    //   100: iadd
    //   101: iconst_0
    //   102: bipush #33
    //   104: aload_1
    //   105: invokevirtual b : (IIIIILbx;)V
    //   108: aload_0
    //   109: getfield aX : Ldq;
    //   112: ifnull -> 145
    //   115: aload_0
    //   116: iconst_0
    //   117: putfield bI : Z
    //   120: aload_0
    //   121: invokestatic a : ()J
    //   124: putfield bQ : J
    //   127: bipush #15
    //   129: aload_0
    //   130: getfield aY : I
    //   133: aload_0
    //   134: getfield aZ : I
    //   137: invokestatic a : (III)V
    //   140: aload_0
    //   141: aconst_null
    //   142: putfield aX : Ldq;
    //   145: aload_0
    //   146: getfield h : I
    //   149: ifne -> 3701
    //   152: aload_1
    //   153: getstatic cg.ao : Laq;
    //   156: aload_0
    //   157: getfield aY : I
    //   160: iconst_1
    //   161: iadd
    //   162: aload_0
    //   163: getfield aZ : I
    //   166: aload_0
    //   167: getfield bo : I
    //   170: isub
    //   171: iconst_5
    //   172: iadd
    //   173: bipush #24
    //   175: isub
    //   176: bipush #17
    //   178: invokevirtual a : (Laq;III)V
    //   181: goto -> 3701
    //   184: aload_0
    //   185: invokespecial aa : ()Z
    //   188: ifne -> 3454
    //   191: aload_0
    //   192: getfield bA : S
    //   195: iconst_m1
    //   196: if_icmpne -> 232
    //   199: aload_0
    //   200: getfield aP : S
    //   203: iconst_m1
    //   204: if_icmpne -> 232
    //   207: aload_1
    //   208: getstatic ez.db : Laq;
    //   211: aload_0
    //   212: getfield aY : I
    //   215: iconst_1
    //   216: iadd
    //   217: aload_0
    //   218: getfield aZ : I
    //   221: aload_0
    //   222: getfield bo : I
    //   225: isub
    //   226: iconst_2
    //   227: iadd
    //   228: iconst_3
    //   229: invokevirtual a : (Laq;III)V
    //   232: aload_0
    //   233: aload_1
    //   234: invokevirtual f : (Lbx;)V
    //   237: aload_0
    //   238: aload_1
    //   239: aload_0
    //   240: getfield aY : I
    //   243: aload_0
    //   244: getfield aZ : I
    //   247: invokevirtual g : (Lbx;II)V
    //   250: aload_0
    //   251: aload_1
    //   252: aload_0
    //   253: getfield aY : I
    //   256: aload_0
    //   257: getfield aZ : I
    //   260: invokevirtual e : (Lbx;II)V
    //   263: aload_0
    //   264: getfield cG : I
    //   267: ifeq -> 286
    //   270: aload_0
    //   271: getfield cG : I
    //   274: iconst_2
    //   275: if_icmpeq -> 286
    //   278: aload_0
    //   279: getfield cG : I
    //   282: iconst_3
    //   283: if_icmpne -> 322
    //   286: aload_0
    //   287: getfield bx : B
    //   290: iconst_3
    //   291: if_icmpne -> 302
    //   294: aload_0
    //   295: getfield ce : I
    //   298: iconst_4
    //   299: if_icmpne -> 318
    //   302: aload_0
    //   303: getfield bx : B
    //   306: iconst_3
    //   307: if_icmpeq -> 322
    //   310: aload_0
    //   311: getfield ce : I
    //   314: iconst_5
    //   315: if_icmpeq -> 322
    //   318: iconst_1
    //   319: goto -> 323
    //   322: iconst_0
    //   323: istore_3
    //   324: aload_0
    //   325: getfield aO : S
    //   328: invokestatic g : (I)Lat;
    //   331: astore #4
    //   333: getstatic ft.ai : I
    //   336: iconst_5
    //   337: irem
    //   338: ifne -> 380
    //   341: aload #4
    //   343: ifnull -> 380
    //   346: aload #4
    //   348: getfield a : Les;
    //   351: invokevirtual c : ()I
    //   354: bipush #18
    //   356: idiv
    //   357: dup
    //   358: istore #5
    //   360: ifne -> 366
    //   363: iconst_1
    //   364: istore #5
    //   366: aload_0
    //   367: aload_0
    //   368: getfield D : B
    //   371: iconst_1
    //   372: iadd
    //   373: iload #5
    //   375: irem
    //   376: i2b
    //   377: putfield D : B
    //   380: aload_0
    //   381: getfield aP : S
    //   384: invokestatic g : (I)Lat;
    //   387: dup
    //   388: astore #5
    //   390: ifnull -> 454
    //   393: aload #5
    //   395: aload_1
    //   396: aload_0
    //   397: getfield aY : I
    //   400: aload_0
    //   401: getfield ec : I
    //   404: iadd
    //   405: aload_0
    //   406: getfield aZ : I
    //   409: aload_0
    //   410: getfield bo : I
    //   413: isub
    //   414: aload_0
    //   415: getfield bj : I
    //   418: isub
    //   419: aload_0
    //   420: getfield bk : I
    //   423: iadd
    //   424: aload_0
    //   425: getfield bw : I
    //   428: isub
    //   429: aload_0
    //   430: getfield ed : I
    //   433: iadd
    //   434: aload_0
    //   435: invokespecial X : ()I
    //   438: aload_0
    //   439: getfield cG : I
    //   442: iconst_3
    //   443: if_icmpne -> 450
    //   446: iconst_2
    //   447: goto -> 451
    //   450: iconst_0
    //   451: invokevirtual j : (Lbx;IIII)V
    //   454: aload_0
    //   455: getfield bA : S
    //   458: iconst_m1
    //   459: if_icmpeq -> 690
    //   462: aload_0
    //   463: getfield bA : S
    //   466: invokestatic c : (S)Lfd;
    //   469: dup
    //   470: astore #5
    //   472: getfield a : Laq;
    //   475: ifnull -> 3629
    //   478: aload_0
    //   479: getfield cF : I
    //   482: dup
    //   483: istore #6
    //   485: aload_0
    //   486: getfield o : [[[I
    //   489: arraylength
    //   490: iconst_1
    //   491: isub
    //   492: if_icmple -> 498
    //   495: iconst_0
    //   496: istore #6
    //   498: aload_0
    //   499: aload #5
    //   501: getfield a : Laq;
    //   504: getfield a : Ljavax/microedition/lcdui/Image;
    //   507: invokestatic b : (Ljavax/microedition/lcdui/Image;)I
    //   510: iconst_3
    //   511: idiv
    //   512: putfield be : I
    //   515: aload_0
    //   516: aload #5
    //   518: getfield a : Laq;
    //   521: getfield a : Ljavax/microedition/lcdui/Image;
    //   524: invokestatic a : (Ljavax/microedition/lcdui/Image;)I
    //   527: iconst_2
    //   528: idiv
    //   529: putfield bd : I
    //   532: aload_0
    //   533: getfield ca : I
    //   536: iconst_4
    //   537: if_icmpeq -> 548
    //   540: aload_0
    //   541: getfield ca : I
    //   544: iconst_2
    //   545: if_icmpne -> 551
    //   548: iconst_3
    //   549: istore #6
    //   551: iconst_0
    //   552: istore #7
    //   554: iconst_0
    //   555: istore #8
    //   557: aload_0
    //   558: getfield o : [[[I
    //   561: iload #6
    //   563: aaload
    //   564: aload_0
    //   565: getfield cG : I
    //   568: iconst_2
    //   569: if_icmple -> 576
    //   572: iconst_2
    //   573: goto -> 580
    //   576: aload_0
    //   577: getfield cG : I
    //   580: aaload
    //   581: aload_0
    //   582: getfield ce : I
    //   585: iaload
    //   586: iconst_3
    //   587: idiv
    //   588: aload_0
    //   589: getfield bd : I
    //   592: imul
    //   593: istore #7
    //   595: aload_0
    //   596: getfield o : [[[I
    //   599: iload #6
    //   601: aaload
    //   602: aload_0
    //   603: getfield cG : I
    //   606: iconst_2
    //   607: if_icmple -> 614
    //   610: iconst_2
    //   611: goto -> 618
    //   614: aload_0
    //   615: getfield cG : I
    //   618: aaload
    //   619: aload_0
    //   620: getfield ce : I
    //   623: iaload
    //   624: iconst_3
    //   625: irem
    //   626: aload_0
    //   627: getfield be : I
    //   630: imul
    //   631: istore #8
    //   633: aload_1
    //   634: aload #5
    //   636: getfield a : Laq;
    //   639: iload #7
    //   641: iload #8
    //   643: aload_0
    //   644: getfield bd : I
    //   647: aload_0
    //   648: getfield be : I
    //   651: aload_0
    //   652: getfield cG : I
    //   655: iconst_2
    //   656: if_icmple -> 663
    //   659: iconst_2
    //   660: goto -> 664
    //   663: iconst_0
    //   664: aload_0
    //   665: getfield aY : I
    //   668: aload_0
    //   669: getfield aZ : I
    //   672: aload_0
    //   673: getfield bj : I
    //   676: isub
    //   677: aload_0
    //   678: getfield bk : I
    //   681: iadd
    //   682: bipush #33
    //   684: invokevirtual a : (Laq;IIIIIIII)V
    //   687: goto -> 3629
    //   690: iload_3
    //   691: ifeq -> 826
    //   694: aload_0
    //   695: aload_1
    //   696: iconst_0
    //   697: invokespecial e : (Lbx;I)V
    //   700: aload #4
    //   702: ifnull -> 826
    //   705: aload_0
    //   706: getfield cF : I
    //   709: iconst_2
    //   710: if_icmpeq -> 826
    //   713: aload #4
    //   715: aload_1
    //   716: aload_0
    //   717: getfield aY : I
    //   720: aload_0
    //   721: getfield aZ : I
    //   724: aload_0
    //   725: getfield ee : B
    //   728: iconst_m1
    //   729: if_icmpeq -> 740
    //   732: aload_0
    //   733: getfield eb : I
    //   736: ineg
    //   737: goto -> 741
    //   740: iconst_0
    //   741: iadd
    //   742: aload_0
    //   743: getfield bk : I
    //   746: iadd
    //   747: aload_0
    //   748: invokespecial Z : ()I
    //   751: aload_0
    //   752: getfield cG : I
    //   755: iconst_3
    //   756: if_icmpne -> 763
    //   759: iconst_2
    //   760: goto -> 764
    //   763: iconst_0
    //   764: invokevirtual i : (Lbx;IIII)V
    //   767: aload #4
    //   769: aload_1
    //   770: aload_0
    //   771: getfield aY : I
    //   774: aload_0
    //   775: getfield aZ : I
    //   778: aload_0
    //   779: getfield ee : B
    //   782: iconst_m1
    //   783: if_icmpeq -> 794
    //   786: aload_0
    //   787: getfield eb : I
    //   790: ineg
    //   791: goto -> 795
    //   794: iconst_0
    //   795: iadd
    //   796: aload_0
    //   797: getfield bk : I
    //   800: iadd
    //   801: aload_0
    //   802: invokespecial Z : ()I
    //   805: aload_0
    //   806: getfield cG : I
    //   809: iconst_3
    //   810: if_icmpne -> 817
    //   813: iconst_2
    //   814: goto -> 818
    //   817: iconst_0
    //   818: invokevirtual a : (Lbx;IIII)V
    //   821: goto -> 826
    //   824: astore #5
    //   826: iconst_0
    //   827: istore #5
    //   829: aload_0
    //   830: getfield aN : S
    //   833: invokestatic g : (I)Lat;
    //   836: astore #6
    //   838: aload_0
    //   839: getfield aQ : S
    //   842: invokestatic g : (I)Lat;
    //   845: astore #7
    //   847: aload_0
    //   848: getfield aT : S
    //   851: invokestatic g : (I)Lat;
    //   854: astore #8
    //   856: aload_0
    //   857: getfield aU : S
    //   860: invokestatic g : (I)Lat;
    //   863: astore #9
    //   865: aload_0
    //   866: getfield aV : S
    //   869: invokestatic g : (I)Lat;
    //   872: astore #10
    //   874: getstatic ft.ai : I
    //   877: bipush #6
    //   879: irem
    //   880: ifne -> 922
    //   883: aload #10
    //   885: ifnull -> 922
    //   888: aload #10
    //   890: getfield a : Les;
    //   893: invokevirtual c : ()I
    //   896: bipush #18
    //   898: idiv
    //   899: dup
    //   900: istore #11
    //   902: ifne -> 908
    //   905: iconst_1
    //   906: istore #11
    //   908: aload_0
    //   909: aload_0
    //   910: getfield t : B
    //   913: iconst_1
    //   914: iadd
    //   915: iload #11
    //   917: irem
    //   918: i2b
    //   919: putfield t : B
    //   922: getstatic ft.ai : I
    //   925: bipush #6
    //   927: irem
    //   928: ifne -> 970
    //   931: aload #9
    //   933: ifnull -> 970
    //   936: aload #9
    //   938: getfield a : Les;
    //   941: invokevirtual c : ()I
    //   944: bipush #18
    //   946: idiv
    //   947: dup
    //   948: istore #11
    //   950: ifne -> 956
    //   953: iconst_1
    //   954: istore #11
    //   956: aload_0
    //   957: aload_0
    //   958: getfield s : B
    //   961: iconst_1
    //   962: iadd
    //   963: iload #11
    //   965: irem
    //   966: i2b
    //   967: putfield s : B
    //   970: getstatic ft.ai : I
    //   973: bipush #10
    //   975: irem
    //   976: ifne -> 1018
    //   979: aload #6
    //   981: ifnull -> 1018
    //   984: aload #6
    //   986: getfield a : Les;
    //   989: invokevirtual c : ()I
    //   992: bipush #18
    //   994: idiv
    //   995: dup
    //   996: istore #11
    //   998: ifne -> 1004
    //   1001: iconst_1
    //   1002: istore #11
    //   1004: aload_0
    //   1005: aload_0
    //   1006: getfield v : I
    //   1009: iconst_1
    //   1010: iadd
    //   1011: iload #11
    //   1013: irem
    //   1014: i2b
    //   1015: putfield v : I
    //   1018: getstatic ft.ai : I
    //   1021: bipush #6
    //   1023: irem
    //   1024: ifne -> 1066
    //   1027: aload #8
    //   1029: ifnull -> 1066
    //   1032: aload #8
    //   1034: getfield a : Les;
    //   1037: invokevirtual c : ()I
    //   1040: bipush #18
    //   1042: idiv
    //   1043: dup
    //   1044: istore #11
    //   1046: ifne -> 1052
    //   1049: iconst_1
    //   1050: istore #11
    //   1052: aload_0
    //   1053: aload_0
    //   1054: getfield r : B
    //   1057: iconst_1
    //   1058: iadd
    //   1059: iload #11
    //   1061: irem
    //   1062: i2b
    //   1063: putfield r : B
    //   1066: getstatic ft.ai : I
    //   1069: bipush #6
    //   1071: irem
    //   1072: ifne -> 1114
    //   1075: aload #7
    //   1077: ifnull -> 1114
    //   1080: aload #7
    //   1082: getfield a : Les;
    //   1085: invokevirtual c : ()I
    //   1088: bipush #18
    //   1090: idiv
    //   1091: dup
    //   1092: istore #11
    //   1094: ifne -> 1100
    //   1097: iconst_1
    //   1098: istore #11
    //   1100: aload_0
    //   1101: aload_0
    //   1102: getfield w : B
    //   1105: iconst_1
    //   1106: iadd
    //   1107: iload #11
    //   1109: irem
    //   1110: i2b
    //   1111: putfield w : B
    //   1114: aload_0
    //   1115: getfield aR : S
    //   1118: invokestatic g : (I)Lat;
    //   1121: astore #11
    //   1123: getstatic ft.ai : I
    //   1126: bipush #6
    //   1128: irem
    //   1129: ifne -> 1171
    //   1132: aload #11
    //   1134: ifnull -> 1171
    //   1137: aload #11
    //   1139: getfield a : Les;
    //   1142: invokevirtual c : ()I
    //   1145: bipush #18
    //   1147: idiv
    //   1148: dup
    //   1149: istore #12
    //   1151: ifne -> 1157
    //   1154: iconst_1
    //   1155: istore #12
    //   1157: aload_0
    //   1158: aload_0
    //   1159: getfield x : B
    //   1162: iconst_1
    //   1163: iadd
    //   1164: iload #12
    //   1166: irem
    //   1167: i2b
    //   1168: putfield x : B
    //   1171: aload_0
    //   1172: getfield cG : I
    //   1175: iconst_1
    //   1176: if_icmpeq -> 1238
    //   1179: aload #6
    //   1181: ifnull -> 1238
    //   1184: aload #6
    //   1186: aload_1
    //   1187: aload_0
    //   1188: getfield aY : I
    //   1191: aload_0
    //   1192: getfield aZ : I
    //   1195: aload_0
    //   1196: getfield ee : B
    //   1199: iconst_m1
    //   1200: if_icmpeq -> 1211
    //   1203: aload_0
    //   1204: getfield eb : I
    //   1207: ineg
    //   1208: goto -> 1212
    //   1211: iconst_0
    //   1212: iadd
    //   1213: aload_0
    //   1214: getfield bk : I
    //   1217: iadd
    //   1218: aload_0
    //   1219: invokespecial s : ()I
    //   1222: aload_0
    //   1223: getfield cG : I
    //   1226: iconst_3
    //   1227: if_icmpne -> 1234
    //   1230: iconst_2
    //   1231: goto -> 1235
    //   1234: iconst_0
    //   1235: invokevirtual k : (Lbx;IIII)V
    //   1238: aload_0
    //   1239: getfield aM : S
    //   1242: invokestatic g : (I)Lat;
    //   1245: astore #12
    //   1247: getstatic ft.ai : I
    //   1250: iconst_5
    //   1251: irem
    //   1252: ifne -> 1294
    //   1255: aload #12
    //   1257: ifnull -> 1294
    //   1260: aload #12
    //   1262: getfield a : Les;
    //   1265: invokevirtual c : ()I
    //   1268: bipush #18
    //   1270: idiv
    //   1271: dup
    //   1272: istore #13
    //   1274: ifne -> 1280
    //   1277: iconst_1
    //   1278: istore #13
    //   1280: aload_0
    //   1281: aload_0
    //   1282: getfield C : B
    //   1285: iconst_1
    //   1286: iadd
    //   1287: iload #13
    //   1289: irem
    //   1290: i2b
    //   1291: putfield C : B
    //   1294: aload #10
    //   1296: ifnull -> 1415
    //   1299: aload_0
    //   1300: getfield aV : S
    //   1303: iconst_m1
    //   1304: if_icmpeq -> 1415
    //   1307: aload #10
    //   1309: aload_1
    //   1310: aload_0
    //   1311: getfield aY : I
    //   1314: aload_0
    //   1315: getfield aZ : I
    //   1318: aload_0
    //   1319: getfield ee : B
    //   1322: iconst_m1
    //   1323: if_icmpeq -> 1334
    //   1326: aload_0
    //   1327: getfield eb : I
    //   1330: ineg
    //   1331: goto -> 1335
    //   1334: iconst_0
    //   1335: iadd
    //   1336: aload_0
    //   1337: getfield bk : I
    //   1340: iadd
    //   1341: aload_0
    //   1342: invokespecial r : ()I
    //   1345: aload_0
    //   1346: getfield cG : I
    //   1349: iconst_3
    //   1350: if_icmpne -> 1357
    //   1353: iconst_2
    //   1354: goto -> 1358
    //   1357: iconst_0
    //   1358: invokevirtual m : (Lbx;IIII)V
    //   1361: aload #10
    //   1363: aload_1
    //   1364: aload_0
    //   1365: getfield aY : I
    //   1368: aload_0
    //   1369: getfield aZ : I
    //   1372: aload_0
    //   1373: getfield ee : B
    //   1376: iconst_m1
    //   1377: if_icmpeq -> 1388
    //   1380: aload_0
    //   1381: getfield eb : I
    //   1384: ineg
    //   1385: goto -> 1389
    //   1388: iconst_0
    //   1389: iadd
    //   1390: aload_0
    //   1391: getfield bk : I
    //   1394: iadd
    //   1395: aload_0
    //   1396: invokespecial r : ()I
    //   1399: aload_0
    //   1400: getfield cG : I
    //   1403: iconst_3
    //   1404: if_icmpne -> 1411
    //   1407: iconst_2
    //   1408: goto -> 1412
    //   1411: iconst_0
    //   1412: invokevirtual e : (Lbx;IIII)V
    //   1415: iconst_0
    //   1416: istore #13
    //   1418: goto -> 3222
    //   1421: getstatic ez.n : [[B
    //   1424: aload_0
    //   1425: getfield cG : I
    //   1428: aaload
    //   1429: iload #13
    //   1431: baload
    //   1432: dup
    //   1433: istore #14
    //   1435: iconst_m1
    //   1436: if_icmpne -> 1501
    //   1439: aload #12
    //   1441: ifnull -> 3219
    //   1444: aload #12
    //   1446: aload_1
    //   1447: aload_0
    //   1448: getfield aY : I
    //   1451: aload_0
    //   1452: getfield aZ : I
    //   1455: aload_0
    //   1456: getfield ee : B
    //   1459: iconst_m1
    //   1460: if_icmpeq -> 1471
    //   1463: aload_0
    //   1464: getfield eb : I
    //   1467: ineg
    //   1468: goto -> 1472
    //   1471: iconst_0
    //   1472: iadd
    //   1473: aload_0
    //   1474: getfield bk : I
    //   1477: iadd
    //   1478: aload_0
    //   1479: invokespecial Y : ()I
    //   1482: aload_0
    //   1483: getfield cG : I
    //   1486: iconst_3
    //   1487: if_icmpne -> 1494
    //   1490: iconst_2
    //   1491: goto -> 1495
    //   1494: iconst_0
    //   1495: invokevirtual l : (Lbx;IIII)V
    //   1498: goto -> 3219
    //   1501: aload_0
    //   1502: getfield cG : I
    //   1505: iconst_1
    //   1506: if_icmpne -> 1744
    //   1509: aload #6
    //   1511: ifnull -> 1622
    //   1514: aload #6
    //   1516: aload_1
    //   1517: aload_0
    //   1518: getfield aY : I
    //   1521: aload_0
    //   1522: getfield aZ : I
    //   1525: aload_0
    //   1526: getfield ee : B
    //   1529: iconst_m1
    //   1530: if_icmpeq -> 1541
    //   1533: aload_0
    //   1534: getfield eb : I
    //   1537: ineg
    //   1538: goto -> 1542
    //   1541: iconst_0
    //   1542: iadd
    //   1543: aload_0
    //   1544: getfield bk : I
    //   1547: iadd
    //   1548: aload_0
    //   1549: invokespecial s : ()I
    //   1552: aload_0
    //   1553: getfield cG : I
    //   1556: iconst_3
    //   1557: if_icmpne -> 1564
    //   1560: iconst_2
    //   1561: goto -> 1565
    //   1564: iconst_0
    //   1565: invokevirtual k : (Lbx;IIII)V
    //   1568: aload #6
    //   1570: aload_1
    //   1571: aload_0
    //   1572: getfield aY : I
    //   1575: aload_0
    //   1576: getfield aZ : I
    //   1579: aload_0
    //   1580: getfield ee : B
    //   1583: iconst_m1
    //   1584: if_icmpeq -> 1595
    //   1587: aload_0
    //   1588: getfield eb : I
    //   1591: ineg
    //   1592: goto -> 1596
    //   1595: iconst_0
    //   1596: iadd
    //   1597: aload_0
    //   1598: getfield bk : I
    //   1601: iadd
    //   1602: aload_0
    //   1603: invokespecial s : ()I
    //   1606: aload_0
    //   1607: getfield cG : I
    //   1610: iconst_3
    //   1611: if_icmpne -> 1618
    //   1614: iconst_2
    //   1615: goto -> 1619
    //   1618: iconst_0
    //   1619: invokevirtual c : (Lbx;IIII)V
    //   1622: iload #14
    //   1624: iconst_2
    //   1625: if_icmpne -> 1870
    //   1628: aload #12
    //   1630: ifnull -> 1870
    //   1633: aload #12
    //   1635: aload_1
    //   1636: aload_0
    //   1637: getfield aY : I
    //   1640: aload_0
    //   1641: getfield aZ : I
    //   1644: aload_0
    //   1645: getfield ee : B
    //   1648: iconst_m1
    //   1649: if_icmpeq -> 1660
    //   1652: aload_0
    //   1653: getfield eb : I
    //   1656: ineg
    //   1657: goto -> 1661
    //   1660: iconst_0
    //   1661: iadd
    //   1662: aload_0
    //   1663: getfield bk : I
    //   1666: iadd
    //   1667: aload_0
    //   1668: invokespecial Y : ()I
    //   1671: aload_0
    //   1672: getfield cG : I
    //   1675: iconst_3
    //   1676: if_icmpne -> 1683
    //   1679: iconst_2
    //   1680: goto -> 1684
    //   1683: iconst_0
    //   1684: invokevirtual l : (Lbx;IIII)V
    //   1687: aload #12
    //   1689: aload_1
    //   1690: aload_0
    //   1691: getfield aY : I
    //   1694: aload_0
    //   1695: getfield aZ : I
    //   1698: aload_0
    //   1699: getfield ee : B
    //   1702: iconst_m1
    //   1703: if_icmpeq -> 1714
    //   1706: aload_0
    //   1707: getfield eb : I
    //   1710: ineg
    //   1711: goto -> 1715
    //   1714: iconst_0
    //   1715: iadd
    //   1716: aload_0
    //   1717: getfield bk : I
    //   1720: iadd
    //   1721: aload_0
    //   1722: invokespecial Y : ()I
    //   1725: aload_0
    //   1726: getfield cG : I
    //   1729: iconst_3
    //   1730: if_icmpne -> 1737
    //   1733: iconst_2
    //   1734: goto -> 1738
    //   1737: iconst_0
    //   1738: invokevirtual d : (Lbx;IIII)V
    //   1741: goto -> 1870
    //   1744: iload #14
    //   1746: iconst_4
    //   1747: if_icmpne -> 1870
    //   1750: aload #12
    //   1752: ifnull -> 1870
    //   1755: aload_0
    //   1756: getfield dU : Z
    //   1759: ifeq -> 1870
    //   1762: aload #12
    //   1764: aload_1
    //   1765: aload_0
    //   1766: getfield aY : I
    //   1769: aload_0
    //   1770: getfield aZ : I
    //   1773: aload_0
    //   1774: getfield ee : B
    //   1777: iconst_m1
    //   1778: if_icmpeq -> 1789
    //   1781: aload_0
    //   1782: getfield eb : I
    //   1785: ineg
    //   1786: goto -> 1790
    //   1789: iconst_0
    //   1790: iadd
    //   1791: aload_0
    //   1792: getfield bk : I
    //   1795: iadd
    //   1796: aload_0
    //   1797: invokespecial Y : ()I
    //   1800: aload_0
    //   1801: getfield cG : I
    //   1804: iconst_3
    //   1805: if_icmpne -> 1812
    //   1808: iconst_2
    //   1809: goto -> 1813
    //   1812: iconst_0
    //   1813: invokevirtual l : (Lbx;IIII)V
    //   1816: aload #12
    //   1818: aload_1
    //   1819: aload_0
    //   1820: getfield aY : I
    //   1823: aload_0
    //   1824: getfield aZ : I
    //   1827: aload_0
    //   1828: getfield ee : B
    //   1831: iconst_m1
    //   1832: if_icmpeq -> 1843
    //   1835: aload_0
    //   1836: getfield eb : I
    //   1839: ineg
    //   1840: goto -> 1844
    //   1843: iconst_0
    //   1844: iadd
    //   1845: aload_0
    //   1846: getfield bk : I
    //   1849: iadd
    //   1850: aload_0
    //   1851: invokespecial Y : ()I
    //   1854: aload_0
    //   1855: getfield cG : I
    //   1858: iconst_3
    //   1859: if_icmpne -> 1866
    //   1862: iconst_2
    //   1863: goto -> 1867
    //   1866: iconst_0
    //   1867: invokevirtual d : (Lbx;IIII)V
    //   1870: iload #14
    //   1872: bipush #6
    //   1874: if_icmpeq -> 1883
    //   1877: iload #14
    //   1879: iconst_4
    //   1880: if_icmpne -> 1939
    //   1883: iload #14
    //   1885: bipush #6
    //   1887: if_icmpne -> 1905
    //   1890: aload_0
    //   1891: getfield cG : I
    //   1894: iconst_1
    //   1895: if_icmpne -> 1905
    //   1898: iload #13
    //   1900: bipush #7
    //   1902: if_icmpeq -> 1939
    //   1905: iload #14
    //   1907: bipush #6
    //   1909: if_icmpne -> 1925
    //   1912: aload_0
    //   1913: getfield cG : I
    //   1916: iconst_1
    //   1917: if_icmpeq -> 1925
    //   1920: iload #13
    //   1922: ifeq -> 1939
    //   1925: iload #14
    //   1927: iconst_4
    //   1928: if_icmpne -> 3085
    //   1931: aload_0
    //   1932: getfield cG : I
    //   1935: iconst_1
    //   1936: if_icmpeq -> 3085
    //   1939: iload #14
    //   1941: bipush #6
    //   1943: if_icmpne -> 2070
    //   1946: aload #11
    //   1948: ifnull -> 2070
    //   1951: aload_0
    //   1952: getfield aR : S
    //   1955: iconst_m1
    //   1956: if_icmpeq -> 2070
    //   1959: aload #11
    //   1961: aload_1
    //   1962: aload_0
    //   1963: getfield aY : I
    //   1966: aload_0
    //   1967: getfield aZ : I
    //   1970: aload_0
    //   1971: getfield ee : B
    //   1974: iconst_m1
    //   1975: if_icmpeq -> 1986
    //   1978: aload_0
    //   1979: getfield eb : I
    //   1982: ineg
    //   1983: goto -> 1987
    //   1986: iconst_0
    //   1987: iadd
    //   1988: aload_0
    //   1989: getfield bk : I
    //   1992: iadd
    //   1993: aload_0
    //   1994: invokespecial u : ()I
    //   1997: aload_0
    //   1998: getfield cG : I
    //   2001: iconst_3
    //   2002: if_icmpne -> 2009
    //   2005: iconst_2
    //   2006: goto -> 2010
    //   2009: iconst_0
    //   2010: invokevirtual p : (Lbx;IIII)V
    //   2013: aload #11
    //   2015: aload_1
    //   2016: aload_0
    //   2017: getfield aY : I
    //   2020: aload_0
    //   2021: getfield aZ : I
    //   2024: aload_0
    //   2025: getfield ee : B
    //   2028: iconst_m1
    //   2029: if_icmpeq -> 2040
    //   2032: aload_0
    //   2033: getfield eb : I
    //   2036: ineg
    //   2037: goto -> 2041
    //   2040: iconst_0
    //   2041: iadd
    //   2042: aload_0
    //   2043: getfield bk : I
    //   2046: iadd
    //   2047: aload_0
    //   2048: invokespecial u : ()I
    //   2051: aload_0
    //   2052: getfield cG : I
    //   2055: iconst_3
    //   2056: if_icmpne -> 2063
    //   2059: iconst_2
    //   2060: goto -> 2064
    //   2063: iconst_0
    //   2064: invokevirtual h : (Lbx;IIII)V
    //   2067: goto -> 3219
    //   2070: aload_0
    //   2071: getfield aV : S
    //   2074: iconst_m1
    //   2075: if_icmpeq -> 2112
    //   2078: aload #10
    //   2080: ifnull -> 2112
    //   2083: iload #14
    //   2085: iconst_1
    //   2086: if_icmpeq -> 3219
    //   2089: iload #14
    //   2091: ifeq -> 3219
    //   2094: iload #14
    //   2096: iconst_3
    //   2097: if_icmpeq -> 3219
    //   2100: iload #14
    //   2102: iconst_5
    //   2103: if_icmpeq -> 3219
    //   2106: iload #14
    //   2108: iconst_2
    //   2109: if_icmpeq -> 3219
    //   2112: iload #14
    //   2114: iconst_1
    //   2115: if_icmpne -> 2242
    //   2118: aload_0
    //   2119: getfield aT : S
    //   2122: iconst_m1
    //   2123: if_icmpeq -> 2242
    //   2126: aload #8
    //   2128: ifnull -> 2242
    //   2131: aload #8
    //   2133: aload_1
    //   2134: aload_0
    //   2135: getfield aY : I
    //   2138: aload_0
    //   2139: getfield aZ : I
    //   2142: aload_0
    //   2143: getfield ee : B
    //   2146: iconst_m1
    //   2147: if_icmpeq -> 2158
    //   2150: aload_0
    //   2151: getfield eb : I
    //   2154: ineg
    //   2155: goto -> 2159
    //   2158: iconst_0
    //   2159: iadd
    //   2160: aload_0
    //   2161: getfield bk : I
    //   2164: iadd
    //   2165: aload_0
    //   2166: invokespecial r : ()I
    //   2169: aload_0
    //   2170: getfield cG : I
    //   2173: iconst_3
    //   2174: if_icmpne -> 2181
    //   2177: iconst_2
    //   2178: goto -> 2182
    //   2181: iconst_0
    //   2182: invokevirtual m : (Lbx;IIII)V
    //   2185: aload #8
    //   2187: aload_1
    //   2188: aload_0
    //   2189: getfield aY : I
    //   2192: aload_0
    //   2193: getfield aZ : I
    //   2196: aload_0
    //   2197: getfield ee : B
    //   2200: iconst_m1
    //   2201: if_icmpeq -> 2212
    //   2204: aload_0
    //   2205: getfield eb : I
    //   2208: ineg
    //   2209: goto -> 2213
    //   2212: iconst_0
    //   2213: iadd
    //   2214: aload_0
    //   2215: getfield bk : I
    //   2218: iadd
    //   2219: aload_0
    //   2220: invokespecial r : ()I
    //   2223: aload_0
    //   2224: getfield cG : I
    //   2227: iconst_3
    //   2228: if_icmpne -> 2235
    //   2231: iconst_2
    //   2232: goto -> 2236
    //   2235: iconst_0
    //   2236: invokevirtual e : (Lbx;IIII)V
    //   2239: goto -> 3219
    //   2242: iload #14
    //   2244: ifne -> 2371
    //   2247: aload_0
    //   2248: getfield aU : S
    //   2251: iconst_m1
    //   2252: if_icmpeq -> 2371
    //   2255: aload #9
    //   2257: ifnull -> 2371
    //   2260: aload #9
    //   2262: aload_1
    //   2263: aload_0
    //   2264: getfield aY : I
    //   2267: aload_0
    //   2268: getfield aZ : I
    //   2271: aload_0
    //   2272: getfield ee : B
    //   2275: iconst_m1
    //   2276: if_icmpeq -> 2287
    //   2279: aload_0
    //   2280: getfield eb : I
    //   2283: ineg
    //   2284: goto -> 2288
    //   2287: iconst_0
    //   2288: iadd
    //   2289: aload_0
    //   2290: getfield bk : I
    //   2293: iadd
    //   2294: aload_0
    //   2295: invokespecial q : ()I
    //   2298: aload_0
    //   2299: getfield cG : I
    //   2302: iconst_3
    //   2303: if_icmpne -> 2310
    //   2306: iconst_2
    //   2307: goto -> 2311
    //   2310: iconst_0
    //   2311: invokevirtual m : (Lbx;IIII)V
    //   2314: aload #9
    //   2316: aload_1
    //   2317: aload_0
    //   2318: getfield aY : I
    //   2321: aload_0
    //   2322: getfield aZ : I
    //   2325: aload_0
    //   2326: getfield ee : B
    //   2329: iconst_m1
    //   2330: if_icmpeq -> 2341
    //   2333: aload_0
    //   2334: getfield eb : I
    //   2337: ineg
    //   2338: goto -> 2342
    //   2341: iconst_0
    //   2342: iadd
    //   2343: aload_0
    //   2344: getfield bk : I
    //   2347: iadd
    //   2348: aload_0
    //   2349: invokespecial q : ()I
    //   2352: aload_0
    //   2353: getfield cG : I
    //   2356: iconst_3
    //   2357: if_icmpne -> 2364
    //   2360: iconst_2
    //   2361: goto -> 2365
    //   2364: iconst_0
    //   2365: invokevirtual e : (Lbx;IIII)V
    //   2368: goto -> 3219
    //   2371: iload #14
    //   2373: iconst_5
    //   2374: if_icmpne -> 2501
    //   2377: aload_0
    //   2378: getfield aQ : S
    //   2381: iconst_m1
    //   2382: if_icmpeq -> 2501
    //   2385: aload #7
    //   2387: ifnull -> 2501
    //   2390: aload #7
    //   2392: aload_1
    //   2393: aload_0
    //   2394: getfield aY : I
    //   2397: aload_0
    //   2398: getfield aZ : I
    //   2401: aload_0
    //   2402: getfield ee : B
    //   2405: iconst_m1
    //   2406: if_icmpeq -> 2417
    //   2409: aload_0
    //   2410: getfield eb : I
    //   2413: ineg
    //   2414: goto -> 2418
    //   2417: iconst_0
    //   2418: iadd
    //   2419: aload_0
    //   2420: getfield bk : I
    //   2423: iadd
    //   2424: aload_0
    //   2425: invokespecial W : ()I
    //   2428: aload_0
    //   2429: getfield cG : I
    //   2432: iconst_3
    //   2433: if_icmpne -> 2440
    //   2436: iconst_2
    //   2437: goto -> 2441
    //   2440: iconst_0
    //   2441: invokevirtual n : (Lbx;IIII)V
    //   2444: aload #7
    //   2446: aload_1
    //   2447: aload_0
    //   2448: getfield aY : I
    //   2451: aload_0
    //   2452: getfield aZ : I
    //   2455: aload_0
    //   2456: getfield ee : B
    //   2459: iconst_m1
    //   2460: if_icmpeq -> 2471
    //   2463: aload_0
    //   2464: getfield eb : I
    //   2467: ineg
    //   2468: goto -> 2472
    //   2471: iconst_0
    //   2472: iadd
    //   2473: aload_0
    //   2474: getfield bk : I
    //   2477: iadd
    //   2478: aload_0
    //   2479: invokespecial W : ()I
    //   2482: aload_0
    //   2483: getfield cG : I
    //   2486: iconst_3
    //   2487: if_icmpne -> 2494
    //   2490: iconst_2
    //   2491: goto -> 2495
    //   2494: iconst_0
    //   2495: invokevirtual f : (Lbx;IIII)V
    //   2498: goto -> 3219
    //   2501: aload_0
    //   2502: iload #13
    //   2504: invokespecial p : (I)I
    //   2507: iflt -> 3044
    //   2510: aload_0
    //   2511: getfield ee : B
    //   2514: iconst_m1
    //   2515: if_icmpne -> 2769
    //   2518: iload #14
    //   2520: bipush #6
    //   2522: if_icmpne -> 2715
    //   2525: aload_0
    //   2526: getfield cG : I
    //   2529: ifeq -> 2548
    //   2532: aload_0
    //   2533: getfield cG : I
    //   2536: iconst_2
    //   2537: if_icmpeq -> 2548
    //   2540: aload_0
    //   2541: getfield cG : I
    //   2544: iconst_3
    //   2545: if_icmpne -> 2715
    //   2548: iload #14
    //   2550: aload_0
    //   2551: iload #13
    //   2553: invokespecial p : (I)I
    //   2556: invokestatic d : (II)Lfe;
    //   2559: aload_1
    //   2560: aload_0
    //   2561: getfield aY : I
    //   2564: aload_0
    //   2565: getfield aZ : I
    //   2568: aload_0
    //   2569: getfield bo : I
    //   2572: isub
    //   2573: aload_0
    //   2574: getfield bj : I
    //   2577: isub
    //   2578: aload_0
    //   2579: getfield bk : I
    //   2582: iadd
    //   2583: aload_0
    //   2584: getfield bw : I
    //   2587: isub
    //   2588: aload_0
    //   2589: getfield cG : I
    //   2592: aload_0
    //   2593: getfield ce : I
    //   2596: invokevirtual a : (Lbx;IIII)V
    //   2599: aload #6
    //   2601: ifnull -> 3085
    //   2604: aload #6
    //   2606: aload_1
    //   2607: aload_0
    //   2608: getfield aY : I
    //   2611: aload_0
    //   2612: getfield aZ : I
    //   2615: aload_0
    //   2616: getfield ee : B
    //   2619: iconst_m1
    //   2620: if_icmpeq -> 2631
    //   2623: aload_0
    //   2624: getfield eb : I
    //   2627: ineg
    //   2628: goto -> 2632
    //   2631: iconst_0
    //   2632: iadd
    //   2633: aload_0
    //   2634: getfield bk : I
    //   2637: iadd
    //   2638: aload_0
    //   2639: invokespecial s : ()I
    //   2642: aload_0
    //   2643: getfield cG : I
    //   2646: iconst_3
    //   2647: if_icmpne -> 2654
    //   2650: iconst_2
    //   2651: goto -> 2655
    //   2654: iconst_0
    //   2655: invokevirtual k : (Lbx;IIII)V
    //   2658: aload #6
    //   2660: aload_1
    //   2661: aload_0
    //   2662: getfield aY : I
    //   2665: aload_0
    //   2666: getfield aZ : I
    //   2669: aload_0
    //   2670: getfield ee : B
    //   2673: iconst_m1
    //   2674: if_icmpeq -> 2685
    //   2677: aload_0
    //   2678: getfield eb : I
    //   2681: ineg
    //   2682: goto -> 2686
    //   2685: iconst_0
    //   2686: iadd
    //   2687: aload_0
    //   2688: getfield bk : I
    //   2691: iadd
    //   2692: aload_0
    //   2693: invokespecial s : ()I
    //   2696: aload_0
    //   2697: getfield cG : I
    //   2700: iconst_3
    //   2701: if_icmpne -> 2708
    //   2704: iconst_2
    //   2705: goto -> 2709
    //   2708: iconst_0
    //   2709: invokevirtual c : (Lbx;IIII)V
    //   2712: goto -> 3085
    //   2715: iload #14
    //   2717: aload_0
    //   2718: iload #13
    //   2720: invokespecial p : (I)I
    //   2723: invokestatic d : (II)Lfe;
    //   2726: aload_1
    //   2727: aload_0
    //   2728: getfield aY : I
    //   2731: aload_0
    //   2732: getfield aZ : I
    //   2735: aload_0
    //   2736: getfield bo : I
    //   2739: isub
    //   2740: aload_0
    //   2741: getfield bj : I
    //   2744: isub
    //   2745: aload_0
    //   2746: getfield bk : I
    //   2749: iadd
    //   2750: aload_0
    //   2751: getfield bw : I
    //   2754: isub
    //   2755: aload_0
    //   2756: getfield cG : I
    //   2759: aload_0
    //   2760: getfield ce : I
    //   2763: invokevirtual a : (Lbx;IIII)V
    //   2766: goto -> 3085
    //   2769: iload #13
    //   2771: iconst_1
    //   2772: if_icmpeq -> 3036
    //   2775: iload #14
    //   2777: bipush #6
    //   2779: if_icmpne -> 2977
    //   2782: aload_0
    //   2783: getfield cG : I
    //   2786: ifeq -> 2805
    //   2789: aload_0
    //   2790: getfield cG : I
    //   2793: iconst_2
    //   2794: if_icmpeq -> 2805
    //   2797: aload_0
    //   2798: getfield cG : I
    //   2801: iconst_3
    //   2802: if_icmpne -> 2977
    //   2805: iload #14
    //   2807: aload_0
    //   2808: iload #13
    //   2810: invokespecial p : (I)I
    //   2813: invokestatic d : (II)Lfe;
    //   2816: aload_1
    //   2817: aload_0
    //   2818: getfield aY : I
    //   2821: aload_0
    //   2822: getfield aZ : I
    //   2825: aload_0
    //   2826: getfield bo : I
    //   2829: isub
    //   2830: aload_0
    //   2831: getfield bj : I
    //   2834: isub
    //   2835: aload_0
    //   2836: getfield bk : I
    //   2839: iadd
    //   2840: aload_0
    //   2841: getfield eb : I
    //   2844: isub
    //   2845: aload_0
    //   2846: getfield bw : I
    //   2849: isub
    //   2850: aload_0
    //   2851: getfield cG : I
    //   2854: aload_0
    //   2855: getfield ce : I
    //   2858: invokevirtual a : (Lbx;IIII)V
    //   2861: aload #6
    //   2863: ifnull -> 3085
    //   2866: aload #6
    //   2868: aload_1
    //   2869: aload_0
    //   2870: getfield aY : I
    //   2873: aload_0
    //   2874: getfield aZ : I
    //   2877: aload_0
    //   2878: getfield ee : B
    //   2881: iconst_m1
    //   2882: if_icmpeq -> 2893
    //   2885: aload_0
    //   2886: getfield eb : I
    //   2889: ineg
    //   2890: goto -> 2894
    //   2893: iconst_0
    //   2894: iadd
    //   2895: aload_0
    //   2896: getfield bk : I
    //   2899: iadd
    //   2900: aload_0
    //   2901: invokespecial s : ()I
    //   2904: aload_0
    //   2905: getfield cG : I
    //   2908: iconst_3
    //   2909: if_icmpne -> 2916
    //   2912: iconst_2
    //   2913: goto -> 2917
    //   2916: iconst_0
    //   2917: invokevirtual k : (Lbx;IIII)V
    //   2920: aload #6
    //   2922: aload_1
    //   2923: aload_0
    //   2924: getfield aY : I
    //   2927: aload_0
    //   2928: getfield aZ : I
    //   2931: aload_0
    //   2932: getfield ee : B
    //   2935: iconst_m1
    //   2936: if_icmpeq -> 2947
    //   2939: aload_0
    //   2940: getfield eb : I
    //   2943: ineg
    //   2944: goto -> 2948
    //   2947: iconst_0
    //   2948: iadd
    //   2949: aload_0
    //   2950: getfield bk : I
    //   2953: iadd
    //   2954: aload_0
    //   2955: invokespecial s : ()I
    //   2958: aload_0
    //   2959: getfield cG : I
    //   2962: iconst_3
    //   2963: if_icmpne -> 2970
    //   2966: iconst_2
    //   2967: goto -> 2971
    //   2970: iconst_0
    //   2971: invokevirtual c : (Lbx;IIII)V
    //   2974: goto -> 3085
    //   2977: iload #14
    //   2979: aload_0
    //   2980: iload #13
    //   2982: invokespecial p : (I)I
    //   2985: invokestatic d : (II)Lfe;
    //   2988: aload_1
    //   2989: aload_0
    //   2990: getfield aY : I
    //   2993: aload_0
    //   2994: getfield aZ : I
    //   2997: aload_0
    //   2998: getfield bo : I
    //   3001: isub
    //   3002: aload_0
    //   3003: getfield bj : I
    //   3006: isub
    //   3007: aload_0
    //   3008: getfield bk : I
    //   3011: iadd
    //   3012: aload_0
    //   3013: getfield eb : I
    //   3016: isub
    //   3017: aload_0
    //   3018: getfield bw : I
    //   3021: isub
    //   3022: aload_0
    //   3023: getfield cG : I
    //   3026: aload_0
    //   3027: getfield ce : I
    //   3030: invokevirtual a : (Lbx;IIII)V
    //   3033: goto -> 3085
    //   3036: aload_0
    //   3037: aload_1
    //   3038: invokespecial m : (Lbx;)V
    //   3041: goto -> 3085
    //   3044: iload #14
    //   3046: ifeq -> 3073
    //   3049: iload #14
    //   3051: iconst_1
    //   3052: if_icmpeq -> 3073
    //   3055: iload #14
    //   3057: iconst_2
    //   3058: if_icmpeq -> 3073
    //   3061: iload #14
    //   3063: iconst_4
    //   3064: if_icmpeq -> 3073
    //   3067: iload #14
    //   3069: iconst_5
    //   3070: if_icmpne -> 3085
    //   3073: iload #5
    //   3075: ifne -> 3085
    //   3078: iconst_1
    //   3079: istore #5
    //   3081: aload_0
    //   3082: invokespecial ac : ()V
    //   3085: iload #14
    //   3087: iconst_3
    //   3088: if_icmpne -> 3219
    //   3091: aload #12
    //   3093: ifnull -> 3219
    //   3096: aload_0
    //   3097: getfield dU : Z
    //   3100: ifne -> 3219
    //   3103: aload_0
    //   3104: getfield cG : I
    //   3107: iconst_1
    //   3108: if_icmpeq -> 3219
    //   3111: aload #12
    //   3113: aload_1
    //   3114: aload_0
    //   3115: getfield aY : I
    //   3118: aload_0
    //   3119: getfield aZ : I
    //   3122: aload_0
    //   3123: getfield ee : B
    //   3126: iconst_m1
    //   3127: if_icmpeq -> 3138
    //   3130: aload_0
    //   3131: getfield eb : I
    //   3134: ineg
    //   3135: goto -> 3139
    //   3138: iconst_0
    //   3139: iadd
    //   3140: aload_0
    //   3141: getfield bk : I
    //   3144: iadd
    //   3145: aload_0
    //   3146: invokespecial Y : ()I
    //   3149: aload_0
    //   3150: getfield cG : I
    //   3153: iconst_3
    //   3154: if_icmpne -> 3161
    //   3157: iconst_2
    //   3158: goto -> 3162
    //   3161: iconst_0
    //   3162: invokevirtual l : (Lbx;IIII)V
    //   3165: aload #12
    //   3167: aload_1
    //   3168: aload_0
    //   3169: getfield aY : I
    //   3172: aload_0
    //   3173: getfield aZ : I
    //   3176: aload_0
    //   3177: getfield ee : B
    //   3180: iconst_m1
    //   3181: if_icmpeq -> 3192
    //   3184: aload_0
    //   3185: getfield eb : I
    //   3188: ineg
    //   3189: goto -> 3193
    //   3192: iconst_0
    //   3193: iadd
    //   3194: aload_0
    //   3195: getfield bk : I
    //   3198: iadd
    //   3199: aload_0
    //   3200: invokespecial Y : ()I
    //   3203: aload_0
    //   3204: getfield cG : I
    //   3207: iconst_3
    //   3208: if_icmpne -> 3215
    //   3211: iconst_2
    //   3212: goto -> 3216
    //   3215: iconst_0
    //   3216: invokevirtual d : (Lbx;IIII)V
    //   3219: iinc #13, 1
    //   3222: iload #13
    //   3224: getstatic ez.n : [[B
    //   3227: aload_0
    //   3228: getfield cG : I
    //   3231: aaload
    //   3232: arraylength
    //   3233: if_icmplt -> 1421
    //   3236: aload_0
    //   3237: getfield cG : I
    //   3240: iconst_1
    //   3241: if_icmpeq -> 3303
    //   3244: aload #6
    //   3246: ifnull -> 3303
    //   3249: aload #6
    //   3251: aload_1
    //   3252: aload_0
    //   3253: getfield aY : I
    //   3256: aload_0
    //   3257: getfield aZ : I
    //   3260: aload_0
    //   3261: getfield ee : B
    //   3264: iconst_m1
    //   3265: if_icmpeq -> 3276
    //   3268: aload_0
    //   3269: getfield eb : I
    //   3272: ineg
    //   3273: goto -> 3277
    //   3276: iconst_0
    //   3277: iadd
    //   3278: aload_0
    //   3279: getfield bk : I
    //   3282: iadd
    //   3283: aload_0
    //   3284: invokespecial s : ()I
    //   3287: aload_0
    //   3288: getfield cG : I
    //   3291: iconst_3
    //   3292: if_icmpne -> 3299
    //   3295: iconst_2
    //   3296: goto -> 3300
    //   3299: iconst_0
    //   3300: invokevirtual c : (Lbx;IIII)V
    //   3303: aload_0
    //   3304: getfield ee : B
    //   3307: iconst_m1
    //   3308: if_icmpeq -> 3316
    //   3311: aload_0
    //   3312: aload_1
    //   3313: invokespecial l : (Lbx;)V
    //   3316: iload_3
    //   3317: ifne -> 3629
    //   3320: aload_0
    //   3321: aload_1
    //   3322: iconst_0
    //   3323: invokespecial e : (Lbx;I)V
    //   3326: aload #4
    //   3328: ifnull -> 3629
    //   3331: aload_0
    //   3332: getfield cF : I
    //   3335: iconst_2
    //   3336: if_icmpeq -> 3629
    //   3339: aload #4
    //   3341: aload_1
    //   3342: aload_0
    //   3343: getfield aY : I
    //   3346: aload_0
    //   3347: getfield aZ : I
    //   3350: aload_0
    //   3351: getfield ee : B
    //   3354: iconst_m1
    //   3355: if_icmpeq -> 3366
    //   3358: aload_0
    //   3359: getfield eb : I
    //   3362: ineg
    //   3363: goto -> 3367
    //   3366: iconst_0
    //   3367: iadd
    //   3368: aload_0
    //   3369: getfield bk : I
    //   3372: iadd
    //   3373: aload_0
    //   3374: invokespecial Z : ()I
    //   3377: aload_0
    //   3378: getfield cG : I
    //   3381: iconst_3
    //   3382: if_icmpne -> 3389
    //   3385: iconst_2
    //   3386: goto -> 3390
    //   3389: iconst_0
    //   3390: invokevirtual i : (Lbx;IIII)V
    //   3393: aload #4
    //   3395: aload_1
    //   3396: aload_0
    //   3397: getfield aY : I
    //   3400: aload_0
    //   3401: getfield aZ : I
    //   3404: aload_0
    //   3405: getfield ee : B
    //   3408: iconst_m1
    //   3409: if_icmpeq -> 3420
    //   3412: aload_0
    //   3413: getfield eb : I
    //   3416: ineg
    //   3417: goto -> 3421
    //   3420: iconst_0
    //   3421: iadd
    //   3422: aload_0
    //   3423: getfield bk : I
    //   3426: iadd
    //   3427: aload_0
    //   3428: invokespecial Z : ()I
    //   3431: aload_0
    //   3432: getfield cG : I
    //   3435: iconst_3
    //   3436: if_icmpne -> 3443
    //   3439: iconst_2
    //   3440: goto -> 3444
    //   3443: iconst_0
    //   3444: invokevirtual a : (Lbx;IIII)V
    //   3447: goto -> 3629
    //   3450: pop
    //   3451: goto -> 3629
    //   3454: iconst_0
    //   3455: istore_3
    //   3456: goto -> 3616
    //   3459: getstatic ez.n : [[B
    //   3462: aload_0
    //   3463: getfield cG : I
    //   3466: aaload
    //   3467: iload_3
    //   3468: baload
    //   3469: dup
    //   3470: istore #4
    //   3472: iconst_4
    //   3473: if_icmpne -> 3613
    //   3476: aload_0
    //   3477: iload_3
    //   3478: invokespecial p : (I)I
    //   3481: iflt -> 3613
    //   3484: aload_0
    //   3485: getfield ee : B
    //   3488: iconst_m1
    //   3489: if_icmpne -> 3545
    //   3492: iload #4
    //   3494: aload_0
    //   3495: iload_3
    //   3496: invokespecial p : (I)I
    //   3499: invokestatic d : (II)Lfe;
    //   3502: aload_1
    //   3503: aload_0
    //   3504: getfield aY : I
    //   3507: aload_0
    //   3508: getfield aZ : I
    //   3511: aload_0
    //   3512: getfield bo : I
    //   3515: isub
    //   3516: aload_0
    //   3517: getfield bj : I
    //   3520: isub
    //   3521: aload_0
    //   3522: getfield bk : I
    //   3525: iadd
    //   3526: aload_0
    //   3527: getfield bw : I
    //   3530: isub
    //   3531: aload_0
    //   3532: getfield cG : I
    //   3535: aload_0
    //   3536: getfield ce : I
    //   3539: invokevirtual a : (Lbx;IIII)V
    //   3542: goto -> 3613
    //   3545: iload_3
    //   3546: iconst_1
    //   3547: if_icmpeq -> 3608
    //   3550: iload #4
    //   3552: aload_0
    //   3553: iload_3
    //   3554: invokespecial p : (I)I
    //   3557: invokestatic d : (II)Lfe;
    //   3560: aload_1
    //   3561: aload_0
    //   3562: getfield aY : I
    //   3565: aload_0
    //   3566: getfield aZ : I
    //   3569: aload_0
    //   3570: getfield bo : I
    //   3573: isub
    //   3574: aload_0
    //   3575: getfield bj : I
    //   3578: isub
    //   3579: aload_0
    //   3580: getfield bk : I
    //   3583: iadd
    //   3584: aload_0
    //   3585: getfield eb : I
    //   3588: isub
    //   3589: aload_0
    //   3590: getfield bw : I
    //   3593: isub
    //   3594: aload_0
    //   3595: getfield cG : I
    //   3598: aload_0
    //   3599: getfield ce : I
    //   3602: invokevirtual a : (Lbx;IIII)V
    //   3605: goto -> 3613
    //   3608: aload_0
    //   3609: aload_1
    //   3610: invokespecial m : (Lbx;)V
    //   3613: iinc #3, 1
    //   3616: iload_3
    //   3617: getstatic ez.n : [[B
    //   3620: aload_0
    //   3621: getfield cG : I
    //   3624: aaload
    //   3625: arraylength
    //   3626: if_icmplt -> 3459
    //   3629: aload_0
    //   3630: getfield aP : S
    //   3633: invokestatic g : (I)Lat;
    //   3636: dup
    //   3637: astore_3
    //   3638: ifnull -> 3701
    //   3641: aload_3
    //   3642: aload_1
    //   3643: aload_0
    //   3644: getfield aY : I
    //   3647: aload_0
    //   3648: getfield ec : I
    //   3651: iadd
    //   3652: aload_0
    //   3653: getfield aZ : I
    //   3656: aload_0
    //   3657: getfield bo : I
    //   3660: isub
    //   3661: aload_0
    //   3662: getfield bj : I
    //   3665: isub
    //   3666: aload_0
    //   3667: getfield bk : I
    //   3670: iadd
    //   3671: aload_0
    //   3672: getfield bw : I
    //   3675: isub
    //   3676: aload_0
    //   3677: getfield ed : I
    //   3680: iadd
    //   3681: aload_0
    //   3682: invokespecial X : ()I
    //   3685: aload_0
    //   3686: getfield cG : I
    //   3689: iconst_3
    //   3690: if_icmpne -> 3697
    //   3693: iconst_2
    //   3694: goto -> 3698
    //   3697: iconst_0
    //   3698: invokevirtual b : (Lbx;IIII)V
    //   3701: aload_0
    //   3702: invokespecial aa : ()Z
    //   3705: ifne -> 3831
    //   3708: aload_0
    //   3709: aload_1
    //   3710: aload_0
    //   3711: getfield aY : I
    //   3714: aload_0
    //   3715: getfield aZ : I
    //   3718: invokevirtual f : (Lbx;II)V
    //   3721: aload_0
    //   3722: getfield dQ : Z
    //   3725: ifne -> 3831
    //   3728: aload_0
    //   3729: getfield cV : Z
    //   3732: ifeq -> 3831
    //   3735: aload_0
    //   3736: getfield bj : I
    //   3739: ifne -> 3831
    //   3742: iconst_1
    //   3743: istore_3
    //   3744: aload_0
    //   3745: getfield cG : I
    //   3748: iconst_2
    //   3749: if_icmpne -> 3758
    //   3752: iinc #3, 2
    //   3755: goto -> 3769
    //   3758: aload_0
    //   3759: getfield cG : I
    //   3762: iconst_3
    //   3763: if_icmpne -> 3769
    //   3766: iinc #3, -2
    //   3769: aload_1
    //   3770: getstatic ez.dd : Laq;
    //   3773: iconst_0
    //   3774: aload_0
    //   3775: getfield cF : I
    //   3778: ifeq -> 3785
    //   3781: iconst_2
    //   3782: goto -> 3786
    //   3785: iconst_0
    //   3786: bipush #17
    //   3788: imul
    //   3789: getstatic ft.ai : I
    //   3792: iconst_2
    //   3793: idiv
    //   3794: iconst_2
    //   3795: irem
    //   3796: bipush #17
    //   3798: imul
    //   3799: iadd
    //   3800: bipush #28
    //   3802: bipush #17
    //   3804: iconst_0
    //   3805: aload_0
    //   3806: getfield aY : I
    //   3809: iload_3
    //   3810: iadd
    //   3811: aload_0
    //   3812: getfield aZ : I
    //   3815: aload_0
    //   3816: getfield bo : I
    //   3819: isub
    //   3820: iconst_2
    //   3821: isub
    //   3822: aload_0
    //   3823: getfield bk : I
    //   3826: iadd
    //   3827: iconst_3
    //   3828: invokevirtual a : (Laq;IIIIIIII)V
    //   3831: aload_0
    //   3832: astore_3
    //   3833: iconst_0
    //   3834: istore #4
    //   3836: goto -> 3872
    //   3839: aload_3
    //   3840: getfield k : Les;
    //   3843: iload #4
    //   3845: invokevirtual a : (I)Ljava/lang/Object;
    //   3848: checkcast at
    //   3851: dup
    //   3852: astore #5
    //   3854: ifnull -> 3869
    //   3857: aload #5
    //   3859: invokevirtual b : ()Z
    //   3862: ifeq -> 3869
    //   3865: iconst_0
    //   3866: goto -> 3885
    //   3869: iinc #4, 1
    //   3872: iload #4
    //   3874: aload_3
    //   3875: getfield k : Les;
    //   3878: invokevirtual c : ()I
    //   3881: if_icmplt -> 3839
    //   3884: iconst_1
    //   3885: ifne -> 3914
    //   3888: aload_0
    //   3889: aload_1
    //   3890: aload_0
    //   3891: getfield aY : I
    //   3894: aload_0
    //   3895: getfield aZ : I
    //   3898: invokevirtual e : (Lbx;II)V
    //   3901: aload_0
    //   3902: aload_1
    //   3903: aload_0
    //   3904: getfield aY : I
    //   3907: aload_0
    //   3908: getfield aZ : I
    //   3911: invokevirtual f : (Lbx;II)V
    //   3914: aload_0
    //   3915: invokespecial aa : ()Z
    //   3918: ifne -> 4057
    //   3921: aload_0
    //   3922: getfield aS : S
    //   3925: invokestatic g : (I)Lat;
    //   3928: dup
    //   3929: astore_3
    //   3930: ifnull -> 4057
    //   3933: getstatic ft.ai : I
    //   3936: iconst_5
    //   3937: irem
    //   3938: ifne -> 3975
    //   3941: aload_3
    //   3942: ifnull -> 3975
    //   3945: aload_3
    //   3946: getfield a : Les;
    //   3949: invokevirtual c : ()I
    //   3952: dup
    //   3953: istore #4
    //   3955: ifne -> 3961
    //   3958: iconst_1
    //   3959: istore #4
    //   3961: aload_0
    //   3962: aload_0
    //   3963: getfield y : B
    //   3966: iconst_1
    //   3967: iadd
    //   3968: iload #4
    //   3970: irem
    //   3971: i2b
    //   3972: putfield y : B
    //   3975: aload_3
    //   3976: aload_1
    //   3977: aload_0
    //   3978: getfield aY : I
    //   3981: aload_0
    //   3982: getfield aZ : I
    //   3985: aload_0
    //   3986: getfield ee : B
    //   3989: iconst_m1
    //   3990: if_icmpeq -> 4001
    //   3993: aload_0
    //   3994: getfield eb : I
    //   3997: ineg
    //   3998: goto -> 4002
    //   4001: iconst_0
    //   4002: iadd
    //   4003: aload_0
    //   4004: getfield bk : I
    //   4007: iadd
    //   4008: aload_0
    //   4009: getfield y : B
    //   4012: iconst_0
    //   4013: invokevirtual o : (Lbx;IIII)V
    //   4016: aload_3
    //   4017: aload_1
    //   4018: aload_0
    //   4019: getfield aY : I
    //   4022: aload_0
    //   4023: getfield aZ : I
    //   4026: aload_0
    //   4027: getfield ee : B
    //   4030: iconst_m1
    //   4031: if_icmpeq -> 4042
    //   4034: aload_0
    //   4035: getfield eb : I
    //   4038: ineg
    //   4039: goto -> 4043
    //   4042: iconst_0
    //   4043: iadd
    //   4044: aload_0
    //   4045: getfield bk : I
    //   4048: iadd
    //   4049: aload_0
    //   4050: getfield y : B
    //   4053: iconst_0
    //   4054: invokevirtual g : (Lbx;IIII)V
    //   4057: aload_0
    //   4058: invokespecial aa : ()Z
    //   4061: ifne -> 4123
    //   4064: getstatic cf.I : Z
    //   4067: ifne -> 4077
    //   4070: aload_0
    //   4071: getstatic cn.h : Lez;
    //   4074: if_acmpeq -> 4088
    //   4077: iload_2
    //   4078: iconst_m1
    //   4079: if_icmpeq -> 4088
    //   4082: aload_0
    //   4083: aload_1
    //   4084: iload_2
    //   4085: invokevirtual a : (Lbx;I)V
    //   4088: aload_0
    //   4089: aload_1
    //   4090: invokevirtual e : (Lbx;)V
    //   4093: aload_0
    //   4094: aload_1
    //   4095: invokespecial k : (Lbx;)V
    //   4098: aload_0
    //   4099: aload_1
    //   4100: aload_0
    //   4101: getfield aY : I
    //   4104: aload_0
    //   4105: getfield aZ : I
    //   4108: invokevirtual d : (Lbx;II)V
    //   4111: aload_0
    //   4112: getfield br : I
    //   4115: ifle -> 4123
    //   4118: aload_0
    //   4119: aload_1
    //   4120: invokevirtual h : (Lbx;)V
    //   4123: return
    // Exception table:
    //   from	to	target	type
    //   694	821	824	java/lang/Exception
    //   3320	3447	3450	java/lang/Exception
  }
  
  public final void d(bx parambx, int paramInt1, int paramInt2) {
    if (!c_() && cg == 1)
      return; 
    for (byte b = 0; b < this.du.c(); b++) {
      dq dq1;
      if ((dq1 = (dq)this.du.a(b)) != null)
        dq1.a(parambx, paramInt1, paramInt2 - this.bq); 
    } 
  }
  
  public final void e(bx parambx, int paramInt1, int paramInt2) {
    if (!c_() && cg == 1)
      return; 
    int i;
    if ((i = this.k.c()) > 0)
      for (byte b = 0; b < i; b++) {
        at at;
        if ((at = (at)this.k.a(b)) != null)
          at.a(parambx, paramInt1, paramInt2); 
      }  
  }
  
  public final void f(bx parambx, int paramInt1, int paramInt2) {
    if (!c_() && cg == 1)
      return; 
    int i;
    if ((i = this.k.c()) > 0)
      for (byte b = 0; b < i; b++) {
        at at;
        if ((at = (at)this.k.a(b)) != null)
          at.b(parambx, paramInt1, paramInt2); 
      }  
  }
  
  public final void g(bx parambx, int paramInt1, int paramInt2) {
    if (!c_() && cg == 1)
      return; 
    for (byte b = 0; b < this.dv.c(); b++) {
      dq dq1;
      if ((dq1 = (dq)this.dv.a(b)) != null)
        dq1.a(parambx, paramInt1, paramInt2 - this.bq); 
    } 
  }
  
  private boolean aa() {
    for (byte b = 0; b < this.k.c(); b++) {
      at at;
      if ((at = (at)this.k.a(b)) != null && at.c())
        return true; 
    } 
    return false;
  }
  
  private boolean ab() {
    int i;
    if ((i = this.du.c()) > 0)
      for (byte b1 = 0; b1 < i; b1++) {
        dq dq1;
        if ((dq1 = (dq)this.du.a(b1)) != null && dq1.d())
          return false; 
      }  
    for (byte b = 0; b < this.k.c(); b++) {
      at at;
      if ((at = (at)this.k.a(b)) != null && at.b())
        return false; 
    } 
    return true;
  }
  
  public final boolean H() {
    if (this.dK || this.dJ || this.dL || this.bI)
      return false; 
    int i;
    if ((i = this.du.c()) > 0)
      for (byte b1 = 0; b1 < i; b1++) {
        dq dq1;
        if ((dq1 = (dq)this.du.a(b1)) != null && dq1.c())
          return false; 
      }  
    if (this.dv.c() > 0)
      for (byte b1 = 0; b1 < this.dv.c(); b1++) {
        dq dq1;
        if ((dq1 = (dq)this.dv.a(b1)) != null && dq1.c())
          return false; 
      }  
    for (byte b = 0; b < this.k.c(); b++) {
      at at;
      if ((at = (at)this.k.a(b)) != null && at.a())
        return false; 
    } 
    return true;
  }
  
  public final void h(bx parambx) {
    if (!this.bI || this.cF == 4)
      return; 
    if (this.bI && this.aX != null)
      this.aX.a(parambx); 
  }
  
  private int p(int paramInt) {
    // Byte code:
    //   0: getstatic ez.n : [[B
    //   3: aload_0
    //   4: getfield cG : I
    //   7: aaload
    //   8: iload_1
    //   9: baload
    //   10: tableswitch default -> 275, 0 -> 52, 1 -> 74, 2 -> 96, 3 -> 135, 4 -> 226, 5 -> 231, 6 -> 253
    //   52: aload_0
    //   53: getfield dF : [S
    //   56: iconst_1
    //   57: saload
    //   58: iconst_m1
    //   59: if_icmpeq -> 69
    //   62: aload_0
    //   63: getfield dF : [S
    //   66: iconst_1
    //   67: saload
    //   68: ireturn
    //   69: aload_0
    //   70: getfield bZ : I
    //   73: ireturn
    //   74: aload_0
    //   75: getfield dF : [S
    //   78: iconst_0
    //   79: saload
    //   80: iconst_m1
    //   81: if_icmpeq -> 91
    //   84: aload_0
    //   85: getfield dF : [S
    //   88: iconst_0
    //   89: saload
    //   90: ireturn
    //   91: aload_0
    //   92: getfield bY : I
    //   95: ireturn
    //   96: aload_0
    //   97: getfield dF : [S
    //   100: arraylength
    //   101: bipush #6
    //   103: if_icmple -> 130
    //   106: aload_0
    //   107: getfield dF : [S
    //   110: bipush #6
    //   112: saload
    //   113: iconst_m1
    //   114: if_icmpeq -> 125
    //   117: aload_0
    //   118: getfield dF : [S
    //   121: bipush #6
    //   123: saload
    //   124: ireturn
    //   125: aload_0
    //   126: getfield bX : I
    //   129: ireturn
    //   130: aload_0
    //   131: getfield bX : I
    //   134: ireturn
    //   135: aload_0
    //   136: astore_1
    //   137: getstatic bq.E : [B
    //   140: ifnonnull -> 147
    //   143: iconst_0
    //   144: goto -> 199
    //   147: aload_1
    //   148: getfield dF : [S
    //   151: iconst_2
    //   152: saload
    //   153: iconst_m1
    //   154: if_icmpeq -> 161
    //   157: iconst_0
    //   158: goto -> 199
    //   161: getstatic bq.E : [B
    //   164: arraylength
    //   165: istore_2
    //   166: iconst_0
    //   167: istore_3
    //   168: goto -> 193
    //   171: getstatic bq.E : [B
    //   174: iload_3
    //   175: baload
    //   176: dup
    //   177: istore #4
    //   179: aload_1
    //   180: getfield cb : I
    //   183: if_icmpne -> 190
    //   186: iconst_1
    //   187: goto -> 199
    //   190: iinc #3, 1
    //   193: iload_3
    //   194: iload_2
    //   195: if_icmplt -> 171
    //   198: iconst_0
    //   199: ifeq -> 204
    //   202: iconst_m1
    //   203: ireturn
    //   204: aload_0
    //   205: getfield dF : [S
    //   208: iconst_2
    //   209: saload
    //   210: iconst_m1
    //   211: if_icmpeq -> 221
    //   214: aload_0
    //   215: getfield dF : [S
    //   218: iconst_2
    //   219: saload
    //   220: ireturn
    //   221: aload_0
    //   222: getfield bW : I
    //   225: ireturn
    //   226: aload_0
    //   227: getfield ca : I
    //   230: ireturn
    //   231: aload_0
    //   232: getfield dF : [S
    //   235: iconst_5
    //   236: saload
    //   237: iconst_m1
    //   238: if_icmpeq -> 248
    //   241: aload_0
    //   242: getfield dF : [S
    //   245: iconst_5
    //   246: saload
    //   247: ireturn
    //   248: aload_0
    //   249: getfield cb : I
    //   252: ireturn
    //   253: aload_0
    //   254: getfield dF : [S
    //   257: iconst_4
    //   258: saload
    //   259: iconst_m1
    //   260: if_icmpeq -> 270
    //   263: aload_0
    //   264: getfield dF : [S
    //   267: iconst_4
    //   268: saload
    //   269: ireturn
    //   270: aload_0
    //   271: getfield cc : I
    //   274: ireturn
    //   275: iconst_m1
    //   276: ireturn
  }
  
  private int q(int paramInt) {
    switch (n[this.cG][paramInt]) {
      case 0:
        return this.bx;
      case 1:
        return this.bx;
      case 2:
        return 0;
      case 3:
        return -1;
      case 4:
        return this.bx + 8;
      case 5:
        return this.bx;
      case 6:
        return -1;
    } 
    return -1;
  }
  
  private void ac() {
    if ((ft.aj - this.bV) / 1000L > 60L) {
      q.a().a((short)this.ct);
      this.bV = ft.aj;
    } 
  }
  
  public final void b(bx parambx, int paramInt1, int paramInt2, int paramInt3) {
    int i = ft.ai / 6 % 2;
    at at1 = g(this.aN);
    at at2 = g(this.aQ);
    at at3 = g(this.aT);
    at at4 = g(this.aR);
    at at5 = g(this.aU);
    if (ft.ai % 6 == 0 && at4 != null) {
      int k;
      if ((k = at4.a.c() / 18) == 0)
        k = 1; 
      this.x = (byte)((this.x + 1) % k);
    } 
    if (ft.ai % 10 == 0 && at1 != null) {
      int k;
      if ((k = at1.a.c() / 18) == 0)
        k = 1; 
      this.v = (byte)((this.v + 1) % k);
    } 
    if (at1 != null && this.cc == -1 && this.dF[4] == -1) {
      at1.k(parambx, paramInt1, paramInt2, m(i), 0);
      at1.c(parambx, paramInt1, paramInt2, m(i), 0);
    } 
    at at6 = g(this.aM);
    at at7 = g(this.aO);
    if (ft.ai % 5 == 0 && at6 != null) {
      int k;
      if ((k = at6.a.c() / 18) == 0)
        k = 1; 
      this.C = (byte)((this.C + 1) % k);
    } 
    if (ft.ai % 6 == 0 && at2 != null) {
      int k;
      if ((k = at2.a.c() / 18) == 0)
        k = 1; 
      this.w = (byte)((this.w + 1) % k);
    } 
    if (ft.ai % 6 == 0 && at3 != null) {
      int k;
      if ((k = at3.a.c() / 18) == 0)
        k = 1; 
      this.r = (byte)((this.r + 1) % k);
    } 
    if (ft.ai % 6 == 0 && at5 != null) {
      int k;
      if ((k = at5.a.c() / 18) == 0)
        k = 1; 
      this.s = (byte)((this.s + 1) % k);
    } 
    if (at7 != null) {
      at7.i(parambx, paramInt1, paramInt2, o(i), 0);
      at7.a(parambx, paramInt1, paramInt2, o(i), 0);
    } 
    parambx.a(db, paramInt1 + 1, paramInt2 + 2, 3);
    am am1;
    int j;
    if ((j = this.dX) != -1 && ak.c(this.bx, j, 0) != null && (am1 = ak.c(this.bx, j, 0)).a != null)
      parambx.a(am1.a, am1.c[paramInt3][0], 0, am1.c[paramInt3][1], am1.d, 0, paramInt1 + am1.b[paramInt3][i][0], paramInt2 + am1.b[paramInt3][i][1], 0); 
    e(parambx, paramInt1, paramInt2);
    for (byte b = 0; b < (n[this.cG]).length - 1; b++) {
      if ((j = n[0][b]) == -1 && at6 != null)
        at6.l(parambx, paramInt1, paramInt2 + 2, n(i), 0); 
      if (j == 5 && this.aQ != -1 && at2 != null) {
        at2.n(parambx, paramInt1, paramInt2 + 2, b(i), 0);
        at2.f(parambx, paramInt1, paramInt2 + 2, b(i), 0);
      } else if (j == 1 && this.aT != -1 && at3 != null) {
        at3.m(parambx, paramInt1, paramInt2 + 2, k(i), 0);
        at3.e(parambx, paramInt1, paramInt2 + 2, k(i), 0);
      } else if (j == 0 && this.aU != -1 && at5 != null) {
        at5.m(parambx, paramInt1, paramInt2 + 2, l(i), 0);
        at5.e(parambx, paramInt1, paramInt2 + 2, l(i), 0);
      } else if (j == 6 && this.aR != -1 && at4 != null) {
        at4.p(parambx, paramInt1, paramInt2 + 2, a(i), 0);
        at4.h(parambx, paramInt1, paramInt2 + 2, a(i), 0);
      } else if (p(b) > -1) {
        if (j == 6 && (this.cc != -1 || this.dF[4] != -1)) {
          ak.d(j, p(b)).a(parambx, paramInt1, paramInt2, paramInt3, i);
          if (at1 != null) {
            at1.k(parambx, paramInt1, paramInt2, m(i), 0);
            at1.c(parambx, paramInt1, paramInt2, m(i), 0);
          } 
        } else {
          ak.d(j, p(b)).a(parambx, paramInt1, paramInt2, paramInt3, i);
        } 
      } 
    } 
    if (at6 != null) {
      at6.l(parambx, paramInt1, paramInt2 + 2, n(i), 0);
      at6.d(parambx, paramInt1, paramInt2 + 2, n(i), 0);
    } 
    f(parambx, paramInt1, paramInt2);
  }
  
  public final void c(bx parambx, int paramInt1, int paramInt2, int paramInt3) {
    int i = ft.ai / 6 % 2;
    parambx.a(db, paramInt1 + 1, paramInt2 + 2, 3);
    am am1;
    int j;
    if ((j = this.dX) != -1 && ak.c(this.bx, j, 0) != null && (am1 = ak.c(this.bx, j, 0)).a != null)
      parambx.a(am1.a, am1.c[this.cG][0], 0, am1.c[this.cG][1], am1.d, 0, paramInt1 + am1.b[this.cG][i][0], paramInt2 + am1.b[this.cG][i][1], 0); 
    for (byte b = 0; b < (n[this.cG]).length - 1; b++) {
      byte b1;
      if ((b1 = n[this.cG][b]) == 5) {
        if (paramInt3 != -1)
          ak.d(5, paramInt3).a(parambx, paramInt1, paramInt2, 0, i); 
      } else if (p(b) > -1) {
        ak.d(b1, p(b)).a(parambx, paramInt1, paramInt2, 0, i);
      } 
    } 
  }
  
  public void b(bx parambx, int paramInt1, int paramInt2) {}
  
  public void a(bx parambx, int paramInt) {
    if (cf.i())
      return; 
    String str = this.cB;
    o o = null;
    o = fl.a(paramInt);
    paramInt = 1;
    byte b1 = 0;
    if (this.cy == 1) {
      if (this.cv > 0)
        paramInt = 0; 
      b1 = 5;
    } 
    if (this.aS != -1)
      paramInt = 0; 
    byte b2 = 18;
    if (cf.I)
      b2 = 12; 
    if (this.di == 7)
      b2 += 8; 
    if (this.cp && cf.I)
      b2 += 6; 
    if (paramInt != 0)
      o.a(parambx, str, this.aY, this.aZ - this.bo - this.bj + this.bk - (this.bI ? 5 : 0) - this.be - b2 - this.eb - this.bw, 2, false); 
    if (this.cu == 0 && this.cy == 1 && paramInt != 0 && !this.cM) {
      b2 += 10;
      o.a(parambx, df.fs, this.aY, this.aZ - this.bo - this.bj + this.bk - (this.bI ? 5 : 0) - this.be - b2 - this.eb - this.bw, 2, false);
    } 
    if (this.cu == 2 && this.dk == null)
      cg.aF.b(this.cn, this.aY - 6, this.aZ - this.bo - this.bj + this.bk - this.be - b2 - 18 - 4 + ft.ai / 2 % 4, 0, parambx); 
    paramInt = 0;
    if ((bq.N != null && this.cX) || this.bG || this.di == 7) {
      int i = 44;
      if (this.cu == 2 || this.di == 7)
        i = this.be + 5; 
      parambx.a(-8714722);
      parambx.c(this.aY - 20, this.aZ - this.bo - this.bj + this.bk - i - b2, 40, 3);
      parambx.a(-579511);
      parambx.c(this.aY - 20, this.aZ - this.bo - this.bj + this.bk - i - b2, 40 * this.br / this.bs, 3);
      paramInt += 5;
    } 
    if (this.cO != null && this.cy != 1) {
      a(parambx, this.aY - 1, this.aZ - this.bo - this.bj + this.bk - this.be - b2 - 8 - paramInt - this.eb - this.bw, 2);
      paramInt += 16;
    } 
    if (this.cv >= 0 && this.cu == 0 && !E()) {
      paramInt += 59;
      cg.aE.b(this.cv * 3 + ft.ai / 3 % 3, this.aY, this.aZ - this.bj + this.bk - this.bo - paramInt + 18 - b2 + b1 - this.eb - this.bw, 0, 33, parambx);
    } 
  }
  
  public final void h(bx parambx, int paramInt1, int paramInt2) {
    String str = c(" - ");
    if (this.cO != null) {
      paramInt1 += 16;
      a(parambx, 58, paramInt2 + 6, -1);
    } 
    o.f.a(parambx, str, paramInt1, paramInt2 - this.eb - this.bw, 0, true);
  }
  
  public void b(bx parambx) {
    if (cf.i())
      return; 
    if (cn.h != null && !cf.I) {
      ez ez1;
      int i = (ez1 = cn.h).aY;
      int j = ez1.aZ - ez1.bo - ez1.bj + ez1.bk - ez1.be;
      byte b1 = 18;
      boolean bool = true;
      byte b2 = 0;
      if (this.cy == 1) {
        if (this.cv > 0)
          bool = false; 
        b2 = 5;
      } 
      o o = o.f;
      if (this.cu == 3)
        o = fl.b(this.cs); 
      if (this.cu == 2 && this.dk == null)
        cg.aF.b(this.cn, i - 6, j - 18 - 18 - 4 + ft.ai / 2 % 4, 0, parambx); 
      if (this.aS == -1)
        o.a(parambx, (new StringBuffer(String.valueOf(this.cB))).toString(), i, j - 18 - this.eb - (this.bI ? 5 : 0) - this.bw, 2, false); 
      byte b3 = 0;
      if (this.cu == 0 && this.cy == 1 && bool && !this.cM) {
        b1 += 10;
        b3 += true;
        o.a(parambx, df.fs, i, j - 28 - this.eb - (this.bI ? 5 : 0) - this.bw, 2, false);
      } 
      if (bq.N != null && ez1.cX)
        b3 = 5; 
      if (this.cO != null && ez1.cy != 1) {
        a(parambx, i, j - b1 - 8 - b3 - this.eb - this.bw, 2);
        b3 += 16;
      } 
      if (ez1.cv >= 0 && ez1.cu == 0 && !E()) {
        b3 += 20;
        cg.aE.b(this.cv * 3 + ft.ai / 3 % 3, i, j - b3 + b2 - this.eb - this.bw, 0, 33, parambx);
      } 
    } 
  }
  
  public static void i(bx parambx) {
    if (cn.h != null && !cf.I && cn.h.cu != 10) {
      ez ez1 = cn.h;
      int i = 1;
      if (ez1.cu == 1) {
        if (!ez1.dR)
          return; 
        i = 4;
        if (ez1.di == 3 || ez1.di == 5 || ez1.di == 10 || ez1.di == 8)
          i = 12; 
      } 
      if (ch == 0) {
        ch = aq.a(da.a);
        ci = aq.b(da.a) / 10;
      } 
      parambx.a(da, 0, g * ci, ch, ci, 0, ez1.aY, ez1.aZ - ez1.be - ez1.bj + ez1.bk - i - ft.ai % 7 - ez1.eb - ez1.bw, 3);
      if ((bq.N != null && ez1.cX) || ez1.bG) {
        i = 64;
        if (ez1.cu == 2)
          i = ez1.be + 23; 
        parambx.a(-8714722);
        parambx.c(ez1.aY - 20, ez1.aZ - i - ez1.eb - ez1.bw, 40, 3);
        parambx.a(-579511);
        parambx.c(ez1.aY - 20, ez1.aZ - i - ez1.eb - ez1.bw, 40 * ez1.br / ez1.bs, 3);
      } 
    } 
  }
  
  public final void I() {
    int i;
    if ((i = this.k.c()) > 0)
      for (byte b = 0; b < i; b++) {
        at at;
        if ((at = (at)this.k.a(b)) != null) {
          at.d();
          if (at.b)
            this.k.d(at); 
        } 
      }  
  }
  
  public void a() {
    this.aY += this.bb;
    this.aZ += this.bc;
    if (this.j) {
      this.bw += this.d;
      this.d += this.p;
      if (this.bw > this.q) {
        this.bw = this.q;
        this.d = -5;
        this.p = -2;
      } 
      if (this.bw <= 0) {
        this.bw = 0;
        this.j = false;
      } 
    } 
    ez ez1;
    if (this.dZ && (ez1 = this).dZ) {
      if (ez1.ct == cn.f.ct) {
        ft.n();
        ez1.cN = null;
      } 
      ez1.bb = 0;
      ez1.bc = 0;
      boolean bool = false;
      int i = ez1.ea - ez1.aZ >> 1;
      ez1.aZ += i;
      if (i <= 0) {
        ez1.aZ = ez1.ea;
        bool = true;
      } 
      if (bool) {
        ez1.bb = 0;
        ez1.bc = 0;
        ez1.cF = 0;
        ez1.bf = ez1.aY;
        ez1.bg = ez1.aZ;
        ez1.ea = ez1.aZ;
        ez1.ea = ez1.aZ;
        ez1.cj = ez1.aY;
        ez1.ck = ez1.aZ;
        ez1.dZ = false;
      } else {
        if (ft.p.a(ez1.aY, ez1.aZ) == 2 && !ez1.ad()) {
          ez1.cV = true;
          ez1.bk = 3;
        } 
        if (ft.ai % 2 == 0) {
          cn.a(9, ez1.aY, ez1.aZ);
          cn.a(46, ez1.aY, ez1.aZ - 2);
        } 
      } 
    } 
    if ((ez1 = this).a > 0) {
      ez1.bj = ez1.a;
      ez1.b++;
      if (ez1.b > 30)
        ez1.a = 30; 
    } else {
      if (ez1.bj > 0) {
        ez1.c -= 2;
        ez1.bj += ez1.c;
      } 
      if (ez1.bj < 0) {
        ez1.bj = -ez1.bj;
        ez1.c = 0;
      } 
      if (ez1.bj < 3)
        ez1.bj = 0; 
      ez1.b = 0;
    } 
    if (this.dk != null) {
      this.dk.d(this.aY, this.aZ - this.be - 30);
      if ((this != cn.f || cn.f.M == null) && this.dk.b())
        this.dk = null; 
    } 
    if (this.bF) {
      this.bR++;
      if (this.bR > 40) {
        this.bR = 0;
        this.bF = false;
      } 
    } 
    for (byte b1 = 0; b1 < this.df.c(); b1++) {
      ei ei1;
      ei ei2;
      if (!(ei2 = ei1 = (ei)this.df.a(b1)).g) {
        if (ei2.h == 4) {
          if (ak.f(2) == 0) {
            en en;
            (en = new en()).a = ak.g(16);
            en.b = ak.g(10);
            if (ei2.i == 3) {
              en.i = ak.g(3);
              en.j = ak.g(2);
            } 
            ei2.n.a(en);
          } 
          for (byte b = 0; b < ei2.n.c(); b++) {
            en en;
            (en = (en)ei2.n.a(b)).a();
            if (en.n >= 3) {
              ei2.n.d(en);
              b--;
            } 
          } 
        } else if (ei2.h == 9) {
          if (ft.ai % 2 == 0) {
            ei ei = ei2;
            int i = ak.c(1, 4);
            for (byte b3 = 0; b3 < i; b3++) {
              ej ej = new ej();
              int j = ak.c(3, 12);
              byte b4 = 0;
              if (j <= 5) {
                ej.h = 16;
                b4 = 2;
              } else if (j <= 8) {
                b4 = 4;
                ej.h = 12;
              } else {
                b4 = 5;
                ej.h = 9;
              } 
              ej.j = (ak.f(5) == 0);
              int k = ei.c + ak.g(15);
              int m = ei.d - ak.g(10);
              ej.a(k, m, k, m - j, 0, -b4, ej.j);
              ej.i = ak.f(3);
              ei.n.a(ej);
            } 
          } 
          for (byte b = 0; b < ei2.n.c(); b++) {
            ej ej;
            (ej = (ej)ei2.n.a(b)).a();
            if (ej.g >= ej.h) {
              ei2.n.d(ej);
              b--;
            } 
          } 
        } else if (ei2.h > 10 && ei2.h < 15) {
          ei2.k = (byte)(ei2.k + 1);
          if (ei2.k > ei2.j.length - 1)
            ei2.k = 0; 
          if (ei2.f - dw.a() < 0L)
            ei2.g = true; 
        } 
        if (ft.ai % 10 == 0 && ei2.h < 11 && ft.aj - ei2.a > ei2.e)
          ei2.g = true; 
        if (ei2.m != null) {
          ei2.l = ei2.m;
          ei2.m = null;
        } 
      } 
      if (ei1.g) {
        this.df.d(ei1);
        b1--;
      } 
    } 
    if (this.dy) {
      this.dz++;
      if (this.dz > 40) {
        this.dy = false;
        this.dz = 0;
      } 
    } 
    if (this.cE != null) {
      a(this.cE, true);
      this.cE = null;
    } 
    if (this.cO != null && this.cO.q)
      this.cO = null; 
    if (this.dK) {
      this.bb = 0;
      this.bc = 0;
      this.bf = this.aY;
      this.bg = this.aZ;
      this.ca = 0;
      if (this.dj || this.bM - dw.a() < 0L) {
        this.dK = false;
        this.bM = dw.a();
      } 
    } 
    if (this.dJ) {
      this.bb = 0;
      this.bc = 0;
      this.bf = this.aY;
      this.bg = this.aZ;
      if (this.dj || this.bN - dw.a() < 0L) {
        this.dJ = false;
        this.bN = dw.a();
      } 
    } 
    if (this.bI) {
      this.bb = 0;
      this.bc = 0;
      this.bf = this.aY;
      this.bg = this.aZ;
      if (this.aX == null)
        this.aX = new dq(51, this.aY, this.aZ, 0, 0, 0, 0); 
      if (this.aX != null)
        this.aX.a(); 
      if (this.dj || this.bQ - dw.a() < 0L) {
        this.bI = false;
        this.bQ = dw.a();
        cn.a(15, this.aY, this.aZ);
        this.aX = null;
      } 
    } 
    if (this.bH) {
      this.bb = 0;
      this.bc = 0;
      this.bf = this.aY;
      this.bg = this.aZ;
      if (this.dj || this.bL - dw.a() < 0L) {
        this.bH = false;
        this.bL = dw.a();
      } 
    } 
    if (this.dL) {
      this.bb = 0;
      this.bc = 0;
      this.bf = this.aY;
      this.bg = this.aZ;
      if (this.dj || this.bO - dw.a() < 0L) {
        this.dL = false;
        this.bO = dw.a();
      } 
    } 
    if (this.dM && (this.dj || (this.bP - dw.a()) / 1000L <= 0L)) {
      this.dM = false;
      this.bP = dw.a();
    } 
    if (i_() && this.cG != 0)
      this.cG = 0; 
    if (this.ee == -1 && this.eb != 0)
      af(); 
    d_();
    ez1 = this;
    byte b2;
    for (b2 = 0; b2 < ez1.du.c(); b2++) {
      dq dq1;
      if ((dq1 = (dq)ez1.du.a(b2)) != null) {
        dq1.a();
        if (dq1.a)
          ez1.du.d(dq1); 
      } 
    } 
    for (b2 = 0; b2 < ez1.dv.c(); b2++) {
      dq dq1;
      if ((dq1 = (dq)ez1.dv.a(b2)) != null) {
        dq1.a();
        if (dq1.a)
          ez1.dv.d(dq1); 
      } 
    } 
    if (cn.h != null) {
      long l1 = cn.h.br;
      long l2 = 10L;
      long l3;
      if (cn.h.bs > 0 && !cf.I && cn.h.cu != 10 && (g = (byte)(int)((l3 = l1 * l2) / cn.h.bs)) > 9)
        g = 9; 
      g = (byte)ak.e(g - 9);
      if (cn.h.cu == 3 || cn.h.cu == 4)
        g = 0; 
    } 
    ez1 = this;
    if (ft.ai % 2 == 0)
      ez1.O = (byte)(ez1.O + 1); 
    if (ez1.O > 4)
      ez1.O = 0; 
    ez1.L++;
    if (ez1.L < ez1.P) {
      if (ez1.eh[0] == -1) {
        if (ez1.K != null)
          ez1.K = null; 
        if (ez1.O != 0)
          ez1.O = 0; 
      } else {
        ez1.K = ei[ez1.eh[0]];
      } 
    } else if (ez1.L >= ez1.P << 1 && ez1.L < ez1.P * 3) {
      if (ez1.eh[1] == -1) {
        if (ez1.K != null)
          ez1.K = null; 
        if (ez1.O != 0)
          ez1.O = 0; 
      } else {
        ez1.K = ei[ez1.eh[1]];
      } 
    } else if (ez1.L >= ez1.P << 2 && ez1.L < ez1.P * 5) {
      if (ez1.eh[2] == -1) {
        if (ez1.K != null)
          ez1.K = null; 
        if (ez1.O != 0)
          ez1.O = 0; 
      } else {
        ez1.K = ei[ez1.eh[2]];
      } 
    } else if (ez1.L >= ez1.P * 6) {
      ez1.L = 0;
      if (ez1.K != null)
        ez1.K = null; 
      if (ez1.O != 0)
        ez1.O = 0; 
    } else {
      if (ez1.K != null)
        ez1.K = null; 
      if (ez1.O != 0)
        ez1.O = 0; 
    } 
    if (ez1.eh[0] != -1 && ez1.K == ei[ez1.eh[0]]) {
      ez1.M = ez1.R[ez1.eh[0]][ez1.cG];
      if (ez1.ce == 1) {
        ez1.N = ez1.S[ez1.eh[0]][ez1.cG] + 1;
      } else {
        ez1.N = ez1.S[ez1.eh[0]][ez1.cG];
      } 
    } 
    if (ez1.eh[1] != -1 && ez1.K == ei[ez1.eh[1]]) {
      ez1.M = ez1.R[ez1.eh[1]][ez1.cG];
      if (ez1.ce == 1) {
        ez1.N = ez1.S[ez1.eh[1]][ez1.cG] + 1;
      } else {
        ez1.N = ez1.S[ez1.eh[1]][ez1.cG];
      } 
    } 
    if (ez1.eh[2] != -1 && ez1.K == ei[ez1.eh[2]]) {
      ez1.M = ez1.R[ez1.eh[2]][ez1.cG];
      if (ez1.ce == 1) {
        ez1.N = ez1.S[ez1.eh[2]][ez1.cG] + 1;
        return;
      } 
      ez1.N = ez1.S[ez1.eh[2]][ez1.cG];
    } 
  }
  
  public final void J() {
    if (this.cF == 4) {
      if (this.ee != -1)
        this.ee = -1; 
      if (this.h == 0) {
        if (ak.f(20) == 0)
          this.h = 1; 
      } else if (ak.f(3) == 0) {
        this.h = 0;
      } 
      this.bI = false;
      this.aX = null;
      if (!ft.B && ak.f(50) == 0) {
        cn.a(69, this.ct, this.cu, this.ct, this.cu, 0, 0);
        if (ak.f(10) == 0)
          cn.a(69, this.ct, this.cu, this.ct, this.cu, 0, 0); 
      } 
      return;
    } 
    switch (this.cF) {
      case 0:
        this.ba++;
        if (this.ba > this.f.length - 1)
          this.ba = 0; 
        this.ce = this.f[this.ba];
        this.A = this.ce;
        return;
      case 1:
        this.ba++;
        if (this.aP != -1) {
          if (this.ba > B.length - 1)
            this.ba = 0; 
        } else if (this.ba > this.cf.length - 1) {
          this.ba = 0;
        } 
        if (this.bb == 0 && this.bc == 0 && this.cN == null) {
          this.cF = 0;
          ak.f(4);
          this.ba = 0;
        } 
        if (this.aP != -1) {
          this.A = B[this.ba];
          this.ce = 3;
        } else {
          this.ce = this.cf[this.ba];
        } 
        if (this.bK && !this.cV && ft.ai % 5 == 0) {
          cn.a(56, this.aY, this.aZ, this.cG, (byte)-1);
          return;
        } 
        break;
      case 2:
        if (this.dg != null) {
          this.dh.c();
          this.dg.a(this);
        } 
        this.E = (byte)(this.E + 1);
        if (this.E > this.f.length - 1)
          this.E = 0; 
        this.A = this.f[this.E];
        break;
    } 
  }
  
  public final void K() {
    if (this.br < this.bv) {
      this.ca = 3;
      return;
    } 
    if (this.ca == 3)
      this.ca = this.bU; 
    if (this.ca != -1) {
      this.bT++;
      if (this.ca < 3 || this.ca == 4 || this.ca == 5) {
        if (this.ca == 4 && this.bT > 2)
          this.ca = 5; 
        if (this.ca == 2) {
          if (this.bT >= 8) {
            this.bT = 0;
            this.ca = this.bU;
            if (this.bx < 2) {
              this.e = ak.c(30, 80);
              return;
            } 
            this.e = ak.c(10, 60);
            return;
          } 
        } else if (this.bT >= 3) {
          this.bT = 0;
          this.ca = this.bU;
          if (this.bx < 2) {
            this.e = ak.c(30, 80);
            return;
          } 
          this.e = ak.c(10, 60);
          return;
        } 
      } else if (this.bT >= this.e) {
        this.bT = 0;
        this.ca = 0;
      } 
    } 
  }
  
  public void h() {
    if (!H() || this.bH) {
      this.bf = this.aY;
      this.bg = this.aZ;
      return;
    } 
    if (this.dZ)
      return; 
    if (ak.e(this.aY - this.bf) > this.bi + Q()) {
      this.bc = 0;
      this.cF = 1;
      if (ak.e(this.aY - this.bf) > this.bi + Q()) {
        if (this.aY > this.bf) {
          this.bb = -(this.bi + Q());
          this.cH = this.cG;
          this.cG = 2;
          return;
        } 
        this.bb = this.bi + Q();
        this.cH = this.cG;
        this.cG = 3;
        return;
      } 
      this.bb = this.bf - this.aY;
      return;
    } 
    if (ak.e(this.aZ - this.bg) > this.bi + Q()) {
      this.bb = 0;
      this.cF = 1;
      if (ak.e(this.aZ - this.bg) > this.bi + Q()) {
        if (this.aZ > this.bg) {
          this.bc = -(this.bi + Q());
          this.cH = this.cG;
          this.cG = 1;
          return;
        } 
        this.bc = this.bi + Q();
        this.cH = this.cG;
        this.cG = 0;
        return;
      } 
      this.bc = this.bg - this.aZ;
      return;
    } 
    if (this.dC) {
      cn.a(43, this.aY, this.aZ);
      cs.t = 10;
      this.cL = true;
    } 
    this.bb = 0;
    this.bc = 0;
  }
  
  public static ez a(int paramInt, byte paramByte) {
    for (int i = cn.i.c() - 1; i >= 0; i--) {
      ez ez1;
      if ((ez1 = (ez)cn.i.a(i)) != null) {
        if (paramByte == 2 && ez1.j() == paramInt)
          return ez1; 
        if (ez1.cu == paramByte && ez1.ct == paramInt)
          return ez1; 
      } 
    } 
    return null;
  }
  
  public static ez e(int paramInt1, int paramInt2) {
    for (byte b = 0; b < cn.i.c(); b++) {
      ez ez1;
      if ((ez1 = (ez)cn.i.a(b)).cu == paramInt2 && ez1.ct == paramInt1)
        return ez1; 
    } 
    return null;
  }
  
  public static int c(int paramInt1, int paramInt2, int paramInt3, int paramInt4) {
    return f(paramInt1 - paramInt3, paramInt2 - paramInt4);
  }
  
  public static int f(int paramInt1, int paramInt2) {
    return ak.h(paramInt1 * paramInt1 + paramInt2 * paramInt2);
  }
  
  private boolean ad() {
    return (this.ee == -1 || ai.a == null) ? false : ((ai.a[this.ee] == 1));
  }
  
  public final void a(boolean paramBoolean) {
    if (this.dZ)
      return; 
    int i;
    if ((i = ft.p.a(this.aY + this.bb, this.aZ + this.bc)) == 2 && !ad()) {
      if (this.bc != 0)
        if (this.bc > 0) {
          this.bc = this.bi + Q() - 1;
        } else {
          this.bc = -(this.bi + Q()) + 1;
        }  
      if (this.bb != 0)
        if (this.bb > 0) {
          this.bb = this.bi + Q() - 1;
        } else {
          this.bb = -(this.bi + Q()) + 1;
        }  
      this.cV = true;
      this.bk = 3;
    } else {
      this.cV = false;
      this.bk = 0;
      if (i == 1) {
        ez ez1 = this;
        int j = ft.p.b(ez1.aY + ez1.bb, ez1.aZ + ez1.bc);
        if (ez1.bc != 0) {
          if (j % ft.p.e > 0 && (ft.p.a(ez1.aY + ez1.bb - cs.l, ez1.aZ + ez1.bc) == 0 || ft.p.a(ez1.aY + ez1.bb - cs.l, ez1.aZ + ez1.bc) == 2) && (ft.p.a(ez1.aY + ez1.bb - cs.l, ez1.aZ) == 0 || ft.p.a(ez1.aY + ez1.bb - cs.l, ez1.aZ) == 2)) {
            ez1.bb = -(ez1.bi + ez1.Q());
            ez1.cG = 2;
            ez1.bc = 0;
          } else if (j % ft.p.e < ft.p.e - 1 && (ft.p.a(ez1.aY + ez1.bb + cs.l, ez1.aZ + ez1.bc) == 0 || ft.p.a(ez1.aY + ez1.bb + cs.l, ez1.aZ + ez1.bc) == 2) && (ft.p.a(ez1.aY + ez1.bb + cs.l, ez1.aZ) == 0 || ft.p.a(ez1.aY + ez1.bb + cs.l, ez1.aZ) == 2)) {
            ez1.bb = ez1.bi + ez1.Q();
            ez1.cG = 3;
            ez1.bc = 0;
          } else {
            ez1.bc = 0;
          } 
        } else if (ez1.bb != 0) {
          if ((ft.p.a(ez1.aY + ez1.bb, ez1.aZ + ez1.bc - cs.l) == 0 || ft.p.a(ez1.aY + ez1.bb, ez1.aZ + ez1.bc - cs.l) == 2) && (ft.p.a(ez1.aY, ez1.aZ + ez1.bc - cs.l) == 0 || ft.p.a(ez1.aY, ez1.aZ + ez1.bc - cs.l) == 2)) {
            ez1.bc = -(ez1.bi + ez1.Q());
            ez1.cG = 1;
          } else if ((ft.p.a(ez1.aY + ez1.bb, ez1.aZ + ez1.bc + cs.l) == 0 || ft.p.a(ez1.aY + ez1.bb, ez1.aZ + ez1.bc + cs.l) == 2) && (ft.p.a(ez1.aY, ez1.aZ + ez1.bc + cs.l) == 0 || ft.p.a(ez1.aY, ez1.aZ + ez1.bc + cs.l) == 2)) {
            ez1.bc = ez1.bi + ez1.Q();
            ez1.cG = 0;
          } 
          ez1.bb = 0;
        } 
        if (ez1.bb == 0 && ez1.bc == 0) {
          ez1.cF = 0;
          ak.f(4);
        } 
      } 
      if (ft.p.a(this.aY, this.aZ) == 2 && !ad()) {
        this.cV = true;
        this.bk = 3;
      } 
    } 
    if (this.bb == 0 && this.bc == 0 && ((i = ft.p.a(this.aY, this.aZ)) == 1 || i == -1)) {
      i = 24;
      int j = this.aY * 1000;
      int k = this.aZ * 1000;
      byte b = 0;
      boolean bool = false;
      do {
        bool = false;
        int m = j + ak.b(b) * i;
        int n = k + ak.a(b) * i;
        int i1;
        if (m >= 0 && n >= 0 && ((i1 = ft.p.a(m / 1000, n / 1000)) == 0 || i1 == 2)) {
          this.aY = m / 1000;
          this.aZ = n / 1000;
          N();
          bool = true;
        } 
        b += true;
        if (b < '')
          continue; 
        b = 0;
        i += 24;
      } while (!bool);
    } 
  }
  
  public final void h(int paramInt) {
    switch (this.cG) {
      case 1:
        this.bc = -paramInt;
        this.bb = 0;
        return;
      case 0:
        this.bc = paramInt;
        this.bb = 0;
        return;
      case 2:
        this.bc = 0;
        this.bb = -paramInt;
        return;
      case 3:
        this.bc = 0;
        this.bb = paramInt;
        break;
    } 
  }
  
  public void c(int paramInt) {
    int i;
    if (ak.e(i = ak.g(3)) > 1)
      paramInt--; 
    switch (this.cG) {
      case 1:
        this.bc = -paramInt;
        this.bb = i;
        break;
      case 0:
        this.bc = paramInt;
        this.bb = i;
        break;
      case 2:
        this.bc = i;
        this.bb = -paramInt;
        break;
      case 3:
        this.bc = i;
        this.bb = paramInt;
        break;
    } 
    if (this.bb == 0 && ak.f(3) == 0) {
      this.dV = 0;
      this.cF = 0;
      this.bb = 0;
      this.bc = 0;
    } 
    if (this.bb > 0) {
      this.cG = 3;
      return;
    } 
    this.cG = 2;
  }
  
  public static boolean d(int paramInt1, int paramInt2, int paramInt3, int paramInt4) {
    return !(paramInt1 < p.d.a - paramInt3 || paramInt1 > p.d.a + ft.W + paramInt3 || paramInt2 < p.d.b - paramInt4 / 2 || paramInt2 > p.d.b + ft.X + paramInt4 * 3 / 2);
  }
  
  public static boolean c(ez paramez) {
    return !(paramez.aY < p.d.a - paramez.bd || paramez.aY > p.d.a + ft.W + paramez.bd || paramez.aZ < p.d.b - paramez.be || paramez.aZ > p.d.b + ft.X + paramez.be * 3 / 2);
  }
  
  public final void L() {
    if (this.aY == this.bf && this.aZ == this.bg)
      return; 
    if (this.dZ)
      return; 
    int i;
    if (this.cM && ((i = ft.p.a(this.aY + this.bb, this.aZ + this.bc)) == 1 || i == -1)) {
      this.cV = false;
      this.bk = 0;
      this.bb = 0;
      this.bc = 0;
      this.aY = this.bf;
      this.aZ = this.bg;
      this.cJ++;
      if (this.cJ >= 10)
        this.cJ = 25; 
      cn.a(35, this.aY, this.aZ - 20);
    } 
    if (ak.e(this.aY - this.bf) > this.bi + Q() || ak.e(this.aZ - this.bg) > this.bi + Q()) {
      p_();
      return;
    } 
    if (this.cF != 2 && this.cF != 3 && this.cF != 4) {
      this.bl = this.aY;
      this.bm = this.aZ;
      this.bf = this.aY;
      this.bg = this.aZ;
      this.bb = 0;
      this.bc = 0;
      this.cF = 0;
      ak.f(4);
    } 
  }
  
  public void z() {
    if (this.dZ)
      return; 
    this.bc = 0;
    this.cF = 1;
    if (ak.e(this.aY - this.bf) >= this.bi + Q()) {
      if (this.aY >= this.bf) {
        this.bb = -(this.bi + Q());
        this.cG = 2;
        return;
      } 
      this.bb = this.bi + Q();
      this.cG = 3;
      return;
    } 
    this.bb = this.bf - this.aY;
  }
  
  public void A() {
    if (this.dZ)
      return; 
    this.bb = 0;
    this.cF = 1;
    if (ak.e(this.aZ - this.bg) >= this.bi + Q()) {
      if (this.aZ > this.bg) {
        this.bc = -(this.bi + Q());
        this.cG = 1;
        return;
      } 
      this.bc = this.bi + Q();
      this.cG = 0;
      return;
    } 
    this.bc = this.bg - this.aZ;
  }
  
  public void p_() {
    if (this.dZ)
      return; 
    if (this.i) {
      if (ak.e(this.aY - this.bf) >= this.bi + Q()) {
        z();
        return;
      } 
      if (ak.e(this.aZ - this.bg) >= this.bi + Q()) {
        A();
        return;
      } 
      this.bb = 0;
      this.bc = 0;
      return;
    } 
    if (ak.e(this.aZ - this.bg) >= this.bi + Q()) {
      A();
      return;
    } 
    if (ak.e(this.aY - this.bf) >= this.bi + Q()) {
      z();
      return;
    } 
    this.bb = 0;
    this.bc = 0;
  }
  
  public final void g(int paramInt1, int paramInt2) {
    if (this.dZ || this.bH || this.bI)
      return; 
    if ((paramInt2 == 1 || paramInt2 == -1) && this.cJ < 12) {
      this.cV = false;
      this.bk = 0;
      this.bb = 0;
      this.bc = 0;
      this.i = !this.i;
      this.cJ++;
      if (this.cJ >= 10) {
        this.cJ = 25;
        return;
      } 
    } else {
      this.cV = false;
      this.bk = 0;
      if (this.cJ > 0)
        this.cJ--; 
      if (paramInt2 == 2 && !ad()) {
        this.cV = true;
        this.bk = 3;
        if (this.bc != 0)
          if (this.bc > 0) {
            this.bc = this.bi + Q() - paramInt1;
          } else {
            this.bc = -(this.bi + Q()) + paramInt1;
          }  
        if (this.bb != 0) {
          if (this.bb > 0) {
            this.bb = this.bi + Q() - paramInt1;
            return;
          } 
          this.bb = -(this.bi + Q()) + paramInt1;
        } 
      } 
    } 
  }
  
  private void d(bx parambx, int paramInt) {
    paramInt = this.bx;
    if (this.dW >= 0) {
      int i;
      ap ap;
      if ((ap = ak.b[paramInt][0][0]) == null) {
        ak.b(paramInt, 0, 0);
        return;
      } 
      if (this.cF != 2 || this.dW < 4) {
        if (this.dW > 1)
          this.dW = 0; 
        if (this.dW < 0)
          this.dW = 0; 
        if (ak.c(paramInt, 0, 0) != null) {
          am am1 = ak.c(paramInt, 0, 0);
          if ((i = this.ce) > 2)
            i = 2; 
          if (am1.a != null) {
            parambx.a(am1.a, am1.c[this.cG][0], 0, am1.c[this.cG][1], am1.d, 0, this.aY + am1.b[this.cG][i][0], this.aZ - this.bo + am1.b[this.cG][i][1] - this.bj + this.bk - this.eb - this.bw, 0);
            n(parambx);
            return;
          } 
        } 
      } else if (this.dW < (i.a[this.cG]).length && i.g != null) {
        parambx.a(i.g, i.a[this.cG][this.dW], i.b[this.cG][this.dW], i.e[this.cG][this.dW], i.f[this.cG][this.dW], 0, this.aY + i.c[this.cG][this.dW], 0 + this.aZ - this.bo + i.d[this.cG][this.dW] - this.bj + this.bk - this.eb - this.bw, 0);
      } 
    } 
  }
  
  private void e(bx parambx, int paramInt) {
    paramInt = this.bx;
    if (this.dW >= 0) {
      int i;
      ap ap;
      if ((ap = ak.b[paramInt][0][0]) == null) {
        ak.b(paramInt, 0, 0);
        return;
      } 
      int j = this.dX;
      if (this.cF != 2 || this.dW < 4) {
        if (this.dW > 1)
          this.dW = 0; 
        if (this.dW < 0)
          this.dW = 0; 
        if (j != -1 && ak.c(paramInt, j, 0) != null) {
          am am1 = ak.c(paramInt, j, 0);
          if ((i = this.ce) > 2)
            i = 2; 
          if (am1.a != null) {
            parambx.a(am1.a, am1.c[this.cG][0], 0, am1.c[this.cG][1], am1.d, 0, this.aY + am1.b[this.cG][i][0], this.aZ - this.bo + am1.b[this.cG][i][1] - this.bj + this.bk - this.eb - this.bw, 0);
            n(parambx);
            return;
          } 
        } 
      } else if (this.dW < (i.a[this.cG]).length && i.g != null) {
        parambx.a(i.g, i.a[this.cG][this.dW], i.b[this.cG][this.dW], i.e[this.cG][this.dW], i.f[this.cG][this.dW], 0, this.aY + i.c[this.cG][this.dW], 0 + this.aZ - this.bo + i.d[this.cG][this.dW] - this.bj + this.bk - this.eb - this.bw, 0);
      } 
    } 
  }
  
  public final void M() {
    this.bf = this.aY;
    this.bg = this.aZ;
    this.bb = 0;
    this.bc = 0;
  }
  
  public void t() {
    this.ba = 0;
    this.cF = 2;
    this.cP = 0;
    this.bb = 0;
    this.bc = 0;
  }
  
  public static void a(au paramau, int paramInt1, int paramInt2) {
    ez ez1;
    if ((ez1 = a(paramInt1, (byte)0)) == null)
      return; 
    byte b1 = 5;
    byte b2 = 0;
    if (paramau != null) {
      int i = 0;
      int j = 0;
      if (paramau.di != 7 && ez1 != null) {
        i = paramau.aY - ez1.aY << 1;
        for (j = paramau.aZ - ez1.aZ << 1; f(i, j) > 20; j = (j << 1) / 3)
          i = (i << 1) / 3; 
        if (paramInt2 == 1) {
          i <<= 1;
          j <<= 1;
        } else if (paramInt2 == 2) {
          while (f(i, j) > 16) {
            i = (i << 1) / 3;
            j = (j << 1) / 3;
          } 
          b1 = 20;
          b2 = 18;
        } 
      } 
      paramau.b(i, j, b1, b2);
    } 
  }
  
  public void k() {}
  
  public final void a(String paramString, boolean paramBoolean) {
    if (this.dk == null)
      this.dk = new cj(); 
    this.dk.a(paramString, true);
    this.dk.d(this.aY, this.aZ - this.be - 30);
  }
  
  public final void N() {
    this.bb = this.bc = 0;
    this.bf = this.aY;
    this.bg = this.aZ;
    if (this.cF != 2 && this.cF != 4) {
      this.cF = 0;
      this.dW = 0;
    } 
  }
  
  public final void O() {
    this.bb = this.bc = 0;
    if (this.cF == 1)
      this.cF = 0; 
  }
  
  public static void a(ez paramez1, ez paramez2) {
    int j = paramez1.aY - paramez2.aY;
    int i = paramez1.aZ - paramez2.aZ;
    if (ak.e(j) > ak.e(i)) {
      if (j > 0) {
        i = 2;
      } else {
        i = 3;
      } 
    } else if (i > 0) {
      i = 1;
    } else {
      i = 0;
    } 
    paramez1.cG = i;
  }
  
  public final void h(int paramInt1, int paramInt2) {
    ei ei1;
    for (byte b = 0; b < this.df.c(); b++) {
      ei ei;
      if ((ei = (ei)this.df.a(b)) != null && ei.h == paramInt1) {
        long l = paramInt2;
        (ei1 = ei).f = dw.a() + l * 1000L;
        return;
      } 
    } 
    ei ei2 = new ei(paramInt1, paramInt2);
    ((ez)super).df.a(ei2);
  }
  
  public final void b(int paramInt1, int paramInt2, int paramInt3) {
    ei ei;
    if ((ei = ei.a(paramInt1, paramInt3)) != null) {
      ei.a = ft.aj;
      ei.e = paramInt2;
      return;
    } 
    ei = new ei(paramInt1, paramInt2, paramInt3);
    this.df.a(ei);
  }
  
  public final void i(int paramInt) {
    this.ca = 1;
    this.bT = 0;
  }
  
  public final es P() {
    es es1 = new es("MainObject vec");
    for (byte b = 0; b < cn.i.c(); b++) {
      ez ez1;
      int i;
      if ((ez1 = (ez)cn.i.a(b)) != null && ez1 != cn.f && ez1 != this && ez1.cu == 0 && (i = c(this.aY, this.aZ, ez1.aY, ez1.aZ - ez1.be / 2)) <= 30)
        es1.a(ez1); 
    } 
    return es1;
  }
  
  public final void i(int paramInt1, int paramInt2) {
    this.bf = paramInt1;
    this.bg = paramInt2;
    paramInt1 = this.bf - this.aY;
    if ((paramInt2 = this.bg - this.aZ) == 0)
      paramInt2 = 1; 
    if (paramInt1 == 0)
      paramInt1 = 1; 
    int i;
    if ((i = f(paramInt1, paramInt2) / (this.bi + Q())) == 0)
      i = 1; 
    this.bb = paramInt1 / i;
    this.bc = paramInt2 / i;
    if (ak.e(this.bb) > ak.e(paramInt1))
      this.bb = paramInt1; 
    if (ak.e(this.bc) > ak.e(paramInt2))
      this.bc = paramInt2; 
    this.bE = i;
  }
  
  public boolean a(ez paramez) {
    return false;
  }
  
  public boolean q_() {
    return false;
  }
  
  public boolean w() {
    return false;
  }
  
  public boolean i_() {
    return (this.dN >= -100 && this.dN < -2);
  }
  
  public int j() {
    return this.ct;
  }
  
  public boolean b() {
    return true;
  }
  
  public boolean j_() {
    return false;
  }
  
  private void k(bx parambx) {
    if (this.dI) {
      this.F++;
      if (this.F > this.G.length - 1)
        this.F = 0; 
      cg.aH.b(this.G[this.F], this.aY, this.aZ + 5, 0, 33, parambx);
    } 
  }
  
  public final int Q() {
    return (this.ee == -1) ? 0 : ai.b[this.ee];
  }
  
  private boolean ae() {
    if (this.ee == -1)
      return false; 
    byte[] arrayOfByte = ai.c[this.ee];
    for (byte b = 0; b < arrayOfByte.length; b++) {
      if (this.ef == arrayOfByte[b] && this.ef != -1)
        return true; 
    } 
    return false;
  }
  
  public void d_() {
    if (this.ee == -1)
      return; 
    at at = g(this.aP);
    if (ft.ai % 5 == 0 && at != null) {
      int i;
      if ((i = at.a.c() / 21) == 0)
        i = 1; 
      this.z = (byte)((this.z + 1) % i);
    } 
    if (this.ee != -1) {
      if (at == null)
        this.cf = H; 
      if (this.cF == 0) {
        if (this.cG == 2) {
          if (this.ce == 1) {
            this.ef = 1;
          } else {
            this.ef = 0;
          } 
          this.ec = ai.f[this.ee][0];
          this.ed = ai.g[this.ee][0];
          this.eb = ai.d[this.ee][0];
          return;
        } 
        if (this.cG == 3) {
          if (this.ce == 1) {
            this.ef = 1;
          } else {
            this.ef = 0;
          } 
          this.ec = ai.f[this.ee][2];
          this.ed = ai.g[this.ee][2];
          this.eb = ai.d[this.ee][1];
          return;
        } 
        if (this.cG == 1) {
          if (this.ce == 1) {
            this.ef = 11;
          } else {
            this.ef = 10;
          } 
          this.ec = ai.f[this.ee][4];
          this.ed = ai.g[this.ee][4];
          this.eb = ai.d[this.ee][2];
          return;
        } 
        if (this.ce == 1) {
          this.ef = 6;
        } else {
          this.ef = 5;
        } 
        this.ec = ai.f[this.ee][6];
        this.ed = ai.g[this.ee][6];
        this.eb = ai.d[this.ee][3];
        return;
      } 
      if (this.cF == 1) {
        this.eg = (byte)(this.eg + 1);
        if (this.cG == 2) {
          if (this.eg > (ai.h[this.ee]).length - 1)
            this.eg = 0; 
          this.ef = ai.h[this.ee][this.eg];
          this.ec = ai.f[this.ee][1];
          this.ed = ai.g[this.ee][1];
          if (this.ef == 3) {
            this.eb = ai.e[this.ee][0];
          } else if (this.ef == 2) {
            this.eb = ai.e[this.ee][1];
          } else {
            this.eb = ai.e[this.ee][2];
          } 
          if (this.eg == 4 && !ad()) {
            cn.a(55, this.aY + 19, this.aZ - 5, this.cG, (byte)-1);
            return;
          } 
        } else if (this.cG == 3) {
          if (this.eg > (ai.h[this.ee]).length - 1)
            this.eg = 0; 
          this.ef = ai.h[this.ee][this.eg];
          this.ec = ai.f[this.ee][3];
          this.ed = ai.g[this.ee][3];
          if (this.ef == 3) {
            this.eb = ai.e[this.ee][3];
          } else if (this.ef == 2) {
            this.eb = ai.e[this.ee][4];
          } else {
            this.eb = ai.e[this.ee][5];
          } 
          if (this.eg == 4 && !ad()) {
            cn.a(55, this.aY - 11, this.aZ - 5, this.cG, (byte)-1);
            return;
          } 
        } else if (this.cG == 1) {
          if (this.eg > (ai.j[this.ee]).length - 1)
            this.eg = 0; 
          this.ef = ai.j[this.ee][this.eg];
          this.ec = ai.f[this.ee][5];
          this.ed = ai.g[this.ee][5];
          if (this.ef == 13) {
            this.eb = ai.e[this.ee][6];
          } else if (this.ef == 12) {
            this.eb = ai.e[this.ee][7];
          } else {
            this.eb = ai.e[this.ee][8];
          } 
          if (this.eg == 4 && !ad()) {
            cn.a(55, this.aY - 14, this.aZ - 7, 3, (byte)-1);
            cn.a(55, this.aY + 16, this.aZ - 7, 2, (byte)-1);
            return;
          } 
        } else {
          if (this.eg > (ai.i[this.ee]).length - 1)
            this.eg = 0; 
          this.ef = ai.i[this.ee][this.eg];
          this.ec = ai.f[this.ee][7];
          this.ed = ai.g[this.ee][7];
          if (this.ef == 8) {
            this.eb = ai.e[this.ee][9];
          } else if (this.ef == 7) {
            this.eb = ai.e[this.ee][10];
          } else {
            this.eb = ai.e[this.ee][11];
          } 
          if (this.eg == 4 && !ad()) {
            cn.a(55, this.aY - 15, this.aZ - 10, 3, (byte)-1);
            cn.a(55, this.aY + 17, this.aZ - 10, 2, (byte)-1);
            return;
          } 
        } 
      } 
    } else {
      af();
    } 
  }
  
  private void af() {
    this.cf = I;
    this.eb = 0;
  }
  
  private void l(bx parambx) {
    if (this.aP != -1)
      return; 
    if (this.ee == -1)
      return; 
    if (this.bI)
      return; 
    ce ce1;
    if ((ce1 = ce.a(this.ee, 3, 5, 0)) != null && ae())
      ce1.a(this.ef, this.aY + this.ec, this.aZ - this.bo - this.bj + this.bk - this.bw + this.ed, (this.cG > 2) ? 2 : 0, 33, parambx); 
  }
  
  private void m(bx parambx) {
    if (this.aP != -1)
      return; 
    if (this.ee == -1)
      return; 
    if (this.bI)
      return; 
    ce ce1;
    if ((ce1 = ce.a(this.ee, 3, 5, 0)) != null && !ae())
      ce1.a(this.ef, this.aY + this.ec, this.aZ - this.bo - this.bj + this.bk - this.bw + this.ed, (this.cG > 2) ? 2 : 0, 33, parambx); 
  }
  
  public final void a(short[][] paramArrayOfshort) {
    this.J = paramArrayOfshort;
    byte b;
    if ((b = this.bx) == 3) {
      b = 2;
    } else if (b == 2) {
      b = 3;
    } 
    this.eh = new byte[(this.J[b + 8]).length];
    for (byte b1 = 0; b1 < this.J.length; b1++) {
      for (byte b2 = 0; b2 < (this.J[b1]).length; b2++) {
        if (this.J[b + 8][b2] >= 23 && this.J[b + 8][b2] <= 27) {
          this.eh[b2] = 0;
        } else if (this.J[b + 8][b2] >= 28 && this.J[b + 8][b2] <= 32) {
          this.eh[b2] = 1;
        } else {
          this.eh[b2] = -1;
        } 
      } 
    } 
  }
  
  private void n(bx parambx) {
    if (this.K != null)
      this.K.c(this.O, this.aY + this.M, this.aZ - this.bo + this.N - this.bj + this.bk - this.eb - this.bw, this.Q[this.cG], 33, parambx); 
  }
  
  public void c(int paramInt1, int paramInt2) {}
  
  public void b(String paramString) {}
  
  public void k_() {}
  
  public final void R() {
    if ((dt = (byte)(dt + 1)) > 10)
      dt = 0; 
    if (this.bt < this.bu / 10) {
      this.dr = true;
    } else {
      this.dr = false;
    } 
    if (this.br < this.bs / 10 && this.br > 0) {
      this.ds = true;
      return;
    } 
    this.ds = false;
  }
  
  public boolean e_() {
    return false;
  }
  
  public final void j(bx parambx) {
    if (this.dw.c() > 0)
      for (byte b = 0; b < this.dw.c(); b++) {
        aa aa;
        if ((aa = (aa)this.dw.a(b)) != null)
          aa.a(parambx, this.aY, this.aZ); 
      }  
  }
  
  public final void S() {
    if (this.dw.c() > 0)
      for (byte b = 0; b < this.dw.c(); b++) {
        aa aa;
        if ((aa = (aa)this.dw.a(b)) != null)
          aa.a(); 
      }  
  }
  
  public final void T() {
    this.dw.d();
  }
  
  public boolean l_() {
    return false;
  }
  
  public void a(String paramString) {}
  
  public final void a(int paramInt1, byte[] paramArrayOfbyte, int paramInt2, int paramInt3) {
    for (byte b = 0; b < this.k.c(); b++) {
      at at1;
      if ((at1 = (at)this.k.a(b)) != null && at1.f == paramInt1)
        this.k.d(at1); 
    } 
    at at = new at(paramArrayOfbyte, (short)paramInt1, paramInt2, paramInt3);
    this.k.a(at);
  }
  
  public final void a(int paramInt1, byte[] paramArrayOfbyte, int paramInt2, int paramInt3, long paramLong, byte paramByte) {
    for (byte b = 0; b < this.k.c(); b++) {
      at at1;
      if ((at1 = (at)this.k.a(b)) != null && at1.f == paramInt1)
        this.k.d(at1); 
    } 
    at at = new at(paramArrayOfbyte, (short)paramInt1, paramInt2, paramInt3, paramLong, paramByte);
    this.k.a(at);
  }
  
  public final void b(int paramInt1, byte[] paramArrayOfbyte, int paramInt2, int paramInt3, long paramLong, byte paramByte) {
    for (byte b = 0; b < this.k.c(); b++) {
      at at1;
      if ((at1 = (at)this.k.a(b)) != null && at1.f == paramInt1)
        this.k.d(at1); 
    } 
    at at;
    (at = new at(paramArrayOfbyte, (short)paramInt1, paramInt2, paramInt3, 0L, paramByte)).h = false;
    at.i = true;
    this.k.a(at);
  }
  
  public final void j(int paramInt) {
    for (byte b = 0; b < this.k.c(); b++) {
      at at;
      if ((at = (at)this.k.a(b)) != null && at.f == paramInt)
        this.k.d(at); 
    } 
  }
  
  public final int U() {
    return this.be;
  }
  
  public final int V() {
    return this.cG;
  }
  
  public boolean n() {
    return false;
  }
  
  static {
    for (byte b = 0; b < dY.length; b++) {
      dY[b] = new am[40][];
      for (byte b1 = 0; b1 < (dY[b]).length; b1++)
        dY[b][b1] = new am[8]; 
    } 
    (new byte[4])[0] = 24;
    (new byte[4])[1] = 21;
    (new byte[4])[2] = 19;
    (new byte[4])[3] = 13;
    (new byte[5])[1] = -1;
  }
}


/* Location:              C:\Users\Administrator\Desktop\HsoMobi.jar!\ez.class
 * Java compiler version: 1 (45.3)
 * JD-Core Version:       1.1.3
 */